Workbook
Name Paving5: 'Project Info Input'!#REF!

Sheet Project Info Input
A2: ESTIMATE INFORMATION
A3: INPUT SHEET
B5: *Fill in Highlighted Cells*
B7: PROJECT INFORMATION | E7: NOTES
B8: Name | C8: Test
B9: Type
B10: Location | C10: Test 1
B11: Client
B12: Estimator
B13: Checked By
B14: New or Renovation
B15: Estimate Date
B16: Last Update
B17: Plans Dated
B18: Specs Dated
B19: Projected Start Date
B21: SCHEDULE INFORMATION
B22: Site Duration | D22: MO
B23: Bldg Duration | D23: MO
B24: Close-out Duration | C24: 0.5 | D24: MO
B25: Project Duration | C25: =SUM(C22:C23) -> 0 | D25: MO
B27: SITE INFORMATION
B28: Site Size (Acres) | D28: AC
B30: BUILDING INFORMATION
B31: Clear Height | C31: 0 | D31: FT
B32: Building Length | C32: 0 | D32: LF
B33: Building Depth | C33: 0 | D33: LF
B34: Roof Area | C34: =C32*C33 -> 0 | D34: SF | E34: adjust SF as necessary to accurately capture total roof SF
B35: Bldg Perimeter | C35: =(C32+C33)*2 -> 0 | D35: LF | E35: adjust LF as necessary to accurately capture total bldg perimeter LF
B36: Floor Areas | I36: Bays & Columns the Depth of Bldg | L36: Bays & Columns the Length of Bldg
B37: Warehouse | C37: =C34-C38-C39-C40-C41-C42 -> 0 | D37: SF
B38: Office | C38: 0 | D38: SF | I38: Depth | J38: =C33 -> 0 | L38: Depth | M38: =C32 -> 0
B39: Office Mezzanine | C39: 0 | D39: SF | I39: Speed Bay(s) | J39: =C52*IF(C48="Cross Dock",2,1) -> 120
B40: Manufacturing | C40: 0 | D40: SF | I40: Interior Bays | J40: =J38-J39 -> -120 | L40: Interior Bays | M40: =M38/C50 -> 0
B41: Maintenance | C41: 0 | D41: SF | I41: Speed Bays | J41: =IF(C48="Cross Dock",2,1) -> 2
B42: Other | C42: 0 | D42: SF | I42: Interior Bays | J42: =J40/C51 -> -2.4
B43: TOTAL: | C43: =IF(SUM(C37:C42)=0,C34,SUM(C37:C42)) -> 0 | D43: SF | I43: TOTAL BAYS | J43: =ROUNDUP(J41+J42,0) -> -1 | L43: TOTAL BAYS | M43: =ROUNDUP(M40,0) -> 0
B44: Total Wall Area - Exterior | I44: Columns | J44: =J43-1 -> -2 | L44: Columns | M44: =M43-1 -> -1
B45: Total Wall Area - Interior
B46: Average Panel Width | C46: 26 | I46: TOTALS
B47: Quantity of Bldg Entries | C47: =IF(C43=0,0,1) -> 0 | I47: BAYS | J47: =M43*J43 -> 0
B48: Dock Configuration | C48: Cross Dock | E48: select from drop down | I48: COLUMNS | J48: =M44*J44 -> 2
B49: Dock Wall Length | C49: =IF(C48="N/A",0,IF(C48="Single Load",C32,C32*2)) -> 0 | D49: LF
B50: Bay Spacing - Width | C50: 54 | D50: LF
B51: Bay Spacing - Depth | C51: 50 | D51: LF
B52: Bay Spacing - Speed Bay Depth | C52: 60 | D52: LF
B54: BUILDING CONCRETE
B55: Spread Footings
B56: Spread Footings - Total CY | C56: 0 | D56: CY | E56: without waste factor | G56: 35 | H56: lbs Dead Load
B57: Perimeter Continuous Footing | G57: =C50 -> 54 | H57: Bay Width
B58: Width | C58: 3 | D58: FT | G58: =C51 -> 50 | H58: Bay Depth
B59: Depth | C59: 1.5 | D59: FT | G59: 2000 | H59: Bearing Capacity of Soil
B60: Waste Factor | C60: 0.1 | D60: PCT | G60: =SQRT(G56*G57*G58/G59) -> 6.8738635 | H60: Approximate Footing Size (feet)
B61: Slabs
B62: Slab-on-Grade | C62: =C43 -> 0 | D62: SF
B63: Select Slab-on-Grade Reinforcement | C63: None | E63: select from drop down
B64: Slab-on-Grade Thickness | C64: 7 | D64: IN
B65: Slab-on-Deck | C65: =IF(C68=0,0,20*20) -> 0 | D65: SF
B66: Tilt Wall | G66: Tilt Panel Qty Factor - Clear Height + "x" Ft.
B67: Panel Area | C67: =C35*(C31+G67) -> 0 | D67: SF | G67: 9
B68: Pump/Electrical Room Tilt Panel Area | C68: =IF(C43=0,0,20*3*14) -> 0 | D68: SF
B70: STEEL
B71: Roof Structure lbs/SF | C71: =IF(C31<33,0.8,IF(AND(C31>32,C31<37),1,1.2)) -> 0.8 | D71: lbs/SF
B72: Roof Access Ladder | C72: =IF(C43=0,0,1) -> 0 | D72: EA
B73: Roof Ladder w/Cage & Landing | C73: 0 | D73: EA
B75: JOISTS & DECKING
B76: Joists & Girders lbs/SF | C76: 2.7 | D76: lbs/SF
B77: Decking Gauge | C77: 22 | D77: GA
B79: ROUGH CARPENTRY
B80: Roof Perimeter Blocking | C80: =C35 -> 0 | D80: LF
B81: Phone Board | C81: =IF(C43=0,0,1) -> 0 | D81: EA
B83: FIRE PROTECTION
B84: ESFR System | C84: =C43 -> 0 | D84: SF
B85: Qualify Type (i.e. K-17, K-22, etc.) | C85: =IF(C31<33,"K-17",IF(AND(C31>33,C31<39),"K-22",IF(C31>39,"K-25","N/A"))) -> K-17
B86: Fire Pump Type | C86: Electric | E86: select from drop down
B87: Above Ground Storage Tank | C87: 0 | D87: EA
B88: Pre-Fab Pump House | C88: 0 | D88: EA
B89: Fire Protection System - Office | C89: 0 | D89: SF
B91: HVAC
B92: Make Up Air Units | C92: =IF(C43=0,0,ROUNDUP(C37*8/C93,0.1)) -> 0 | D92: EA | E92: Assumes Freeze Protection Only | I92: BTU | J92: CFM
B93: MAU/Heater BTUs | C93: =IF(C34=0,0,F93) -> 0 | D93: BTU | E93: MUA BTU Drop Down | F93: 2100000 | I93: 800000 | J93: 35000
B94: Air Changes Per Hour | C94: 1 | D94: AC/HR | I94: 1200000 | J94: 45000
B95: Exhuast Fan CFM | C95: =F95 -> 50000 | D95: CFM | E95: CFM Drop Down | F95: 50000 | I95: 1600000 | J95: 50000
B96: Exhaust Fans | C96: =ROUNDUP(C43*(C31)*C94*(1-C97)/C95/60,0.1) -> 0 | D96: EA | E96: Vent is to clear hght only | I96: 1850000
B97: Warehouse Fill Factor | C97: 0 | D97: Percent | E97: Input Fill Factor Assumption | I97: 2100000
B98: Exhaust Fan @ Elec/FP Rooms | C98: =IF(C43=0,0,1) -> 0 | D98: EA
B100: ELECTRICAL
B101: Service Size | C101: =ROUNDUP(F101,-3) -> 0 | D101: Amps | E101: Amperage Calculation | F101: =C43*3/831*1.25 -> 0
B102: House Panel | C102: =IF(C43=0,0,200) -> 0 | D102: Amps | F102: https://www.visual-3d.com/tools/interior/
B103: Warehouse Conveniance Outlets | C103: 0 | D103: EA | F103: Lighting Table
B104: Outlets at Dock Doors | C104: 0 | D104: EA | F104: Lumen Output | H104: 24000 | I104: 30000 | J104: 36000
B105: Warehouse Lighting Type | C105: LED | F105: 20 | G105: FC | H105: =$C$37/1250 -> 0 | I105: =$C$37/1500 -> 0 | J105: =$C$37/1815 -> 0
B106: Warehouse Foot Candles | C106: 30 | D106: FC | F106: 25 | G106: FC | H106: =$C$37/1000 -> 0 | I106: =$C$37/1200 -> 0 | J106: =$C$37/1450 -> 0
B107: Warehouse Fixture Lumens | C107: 36000 | F107: 30 | G107: FC | H107: =$C$37/840 -> 0 | I107: =$C$37/1000 -> 0 | J107: =$C$37/1200 -> 0
B108: Warehouse Fixture Count (Open Floor Plan) | C108: =ROUNDUP(INDEX(F104:J107,MATCH(C106,F104:F107,0),MATCH(C107,F104:J104,0)),0) -> 0
F109: Light Fixture - IBGXX000LM SEF L/Lens GND 50K 80CRI
F110: https://lithonia.acuitybrands.com/products/detail/593818/lithonia-lighting/ibg-high-bay/i-beamr-ibg-configurable-led-high-bay

Sheet Budget Summary
D2: Client: | E2: =+'Project Info Input'!C11 -> 0 | G2: =+E90 -> 6568.0722 | I2: Grand Total
D3: Project Name: | E3: ='Project Info Input'!C8 -> Test | G3: =F90 -> 0 | I3: /BSF
D4: Location: | E4: ='Project Info Input'!C10 -> Test 1 | G4: ='Project Info Input'!C31 -> 0 | I4: Clear Height
D5: Date: | E5: =IF('Project Info Input'!C16="",'Project Info Input'!C15,'Project Info Input'!C16) -> 0 | G5: =IF('Project Info Input'!C25=0,0,Estimate!I5) -> 0 | I5: Bldg Footprint to Site Ratio
D6: Building Size (SF): | E6: ='Project Info Input'!C43 -> 0 | G6: =IF('Project Info Input'!C25=0,0,Estimate!I6) -> 0 | I6: Wall to Floor Ratio
D7: Size (Acres): | E7: ='Project Info Input'!C28 -> 0 | G7: =IF('Project Info Input'!C25=0,0,Estimate!I7) -> 0 | I7: Pvg to Floor Ratio
B9: Category | C9: CSI Code | D9: Scope of Work | E9: Cost | F9: Cost/SF | G9: Comments
B11: Site Work | C11: 02 40 00 | D11: Demolition | E11: =Estimate!N23 -> 0 | F11: =IF($E$6=0,0,E11/$E$6) -> 0
C12: 31 00 00 | D12: Earthwork | E12: =Estimate!N55 -> 0 | F12: =IF($E$6=0,0,E12/$E$6) -> 0
C13: 31 25 00 | D13: Erosion Control | E13: =Estimate!N39 -> 0 | F13: =IF($E$6=0,0,E13/$E$6) -> 0
C14: 33 10 00 | D14: Site Utilities | E14: =Estimate!N142+Estimate!N166+Estimate!N178+Estimate!N266 -> 0 | F14: =IF($E$6=0,0,E14/$E$6) -> 0
C15: 33 40 00 | D15: Storm Sewer | E15: =Estimate!N96 -> 0 | F15: =IF($E$6=0,0,E15/$E$6) -> 0
C16: 32 00 00 | D16: Concrete Paving | E16: =Estimate!N200 -> 0 | F16: =IF($E$6=0,0,E16/$E$6) -> 0
C17: 32 12 00 | D17: Asphalt Paving | E17: =Estimate!N234 -> 0 | F17: =IF($E$6=0,0,E17/$E$6) -> 0
C18: 32 17 00 | D18: Pavement Markings | E18: =Estimate!N249 -> 0 | F18: =IF($E$6=0,0,E18/$E$6) -> 0
C19: 32 90 00 | D19: Landscaping | E19: =Estimate!N273 -> 0 | F19: =IF($E$6=0,0,E19/$E$6) -> 0
C20: 32 31 00 | D20: Fencing | E20: =Estimate!N285 -> 0 | F20: =IF($E$6=0,0,E20/$E$6) -> 0
C21: 32 32 00 | D21: Retaining Walls | E21: =Estimate!N301 -> 0 | F21: =IF($E$6=0,0,E21/$E$6) -> 0
C22: 32 30 00 | D22: Misc. Site Improvements | E22: =Estimate!N311 -> 0 | F22: =IF($E$6=0,0,E22/$E$6) -> 0
D23: Subtotal - Site Work | E23: =SUM(E11:E22) -> 0 | F23: =IF($E$6=0,0,E23/$E$6) -> 0 | G23: /BSF | L23: =IF(E23=Estimate!N22,"SITEWORK CHECKS","ERROR - CHECK SUMS") -> SITEWORK CHECKS | M23: =E23 -> 0 | N23: =Estimate!N22 -> 0 | O23: =M23-N23 -> 0
F24: =IF($E$7=0,0,E23/$E$7) -> 0 | G24: /ACRE
B26: Building | C26: 03 30 00 | D26: Foundations | E26: =Estimate!N330 -> 0 | F26: =IF($E$6=0,0,E26/$E$6) -> 0
C27: 03 30 00 | D27: Concrete Slab | E27: =Estimate!N362 -> 0 | F27: =IF($E$6=0,0,E27/$E$6) -> 0
C28: 09 33 00 | D28: Concrete Floor Sealer | E28: =Estimate!N382 -> 0 | F28: =IF($E$6=0,0,E28/$E$6) -> 0
C29: 03 47 00 | D29: Concrete Tilt Walls | E29: =Estimate!N390 -> 0 | F29: =IF($E$6=0,0,E29/$E$6) -> 0
C30: 03 48 00 | D30: Misc. Concrete | E30: =Estimate!N404 -> 0 | F30: =IF($E$6=0,0,E30/$E$6) -> 0
C31: 04 00 00 | D31: Masonry | E31: =Estimate!N417 -> 0 | F31: =IF($E$6=0,0,E31/$E$6) -> 0
C32: 05 00 00 | D32: Structural Steel & Erection | E32: =Estimate!N429+Estimate!N478+Estimate!N495 -> 0 | F32: =IF($E$6=0,0,E32/$E$6) -> 0
C33: 05 50 00 | D33: Misc. Metals | E33: =Estimate!N455 -> 4500 | F33: =IF($E$6=0,0,E33/$E$6) -> 0
C34: 06 10 00 | D34: Rough Carpentry | E34: =Estimate!N511 -> 0 | F34: =IF($E$6=0,0,E34/$E$6) -> 0
C35: 06 20 00 | D35: Finish Carpentry | E35: =Estimate!N519 -> 0 | F35: =IF($E$6=0,0,E35/$E$6) -> 0
C36: 07 00 00 | D36: Insulation | E36: =Estimate!N540 -> 0 | F36: =IF($E$6=0,0,E36/$E$6) -> 0
C37: 07 40 00 | D37: Canopies | E37: =Estimate!N559 -> 0 | F37: =IF($E$6=0,0,E37/$E$6) -> 0
C38: 07 42 00 | D38: Insulated Metal Wall Panels | E38: =Estimate!N570 -> 0 | F38: =IF($E$6=0,0,E38/$E$6) -> 0
C39: 07 50 00 | D39: Roofing | E39: =Estimate!N582 -> 0 | F39: =IF($E$6=0,0,E39/$E$6) -> 0
C40: 07 92 00 | D40: Sealants & Caulking | E40: =Estimate!N607 -> 0 | F40: =IF($E$6=0,0,E40/$E$6) -> 0
C41: 08 00 00 | D41: Doors, Frames & Hardware | E41: =Estimate!N624+Estimate!N635 -> 550 | F41: =IF($E$6=0,0,E41/$E$6) -> 0
C42: 08 30 00 | D42: Overhead Doors | E42: =Estimate!N647 -> 0 | F42: =IF($E$6=0,0,E42/$E$6) -> 0
C43: 08 40 00 | D43: Storefront, Glass & Glazing | E43: =Estimate!N665 -> 0 | F43: =IF($E$6=0,0,E43/$E$6) -> 0
C44: 09 20 00 | D44: Framing & Drywall | E44: =Estimate!N687 -> 0 | F44: =IF($E$6=0,0,E44/$E$6) -> 0
C45: 09 51 00 | D45: Acoustical Ceilings | E45: =Estimate!N704 -> 0 | F45: =IF($E$6=0,0,E45/$E$6) -> 0
C46: 09 60 00 | D46: Flooring | E46: =Estimate!N713 -> 0 | F46: =IF($E$6=0,0,E46/$E$6) -> 0
C47: 09 90 00 | D47: Painting | E47: =Estimate!N734+Estimate!N753+Estimate!N780 -> 0 | F47: =IF($E$6=0,0,E47/$E$6) -> 0
C48: 10 00 00 | D48: Specialties | E48: =Estimate!N796 -> 0 | F48: =IF($E$6=0,0,E48/$E$6) -> 0
C49: 11 30 00 | D49: Loading Dock Equipment | E49: =Estimate!N832 -> 0 | F49: =IF($E$6=0,0,E49/$E$6) -> 0
C50: 11 41 00 | D50: Foodservice Equipment | E50: =Estimate!N854 -> 0 | F50: =IF($E$6=0,0,E50/$E$6) -> 0
C51: 12 00 00 | D51: Furnishings | E51: =Estimate!N872 -> 0 | F51: =IF($E$6=0,0,E51/$E$6) -> 0
C52: 13 12 00 | D52: PEMB | E52: =Estimate!N882 -> 0 | F52: =IF($E$6=0,0,E52/$E$6) -> 0
C53: 14 00 00 | D53: Elevators/Conveying Equipment | E53: =Estimate!N892 -> 0 | F53: =IF($E$6=0,0,E53/$E$6) -> 0
C54: 21 00 00 | D54: Fire Protection | E54: =Estimate!N911 -> 0 | F54: =IF($E$6=0,0,E54/$E$6) -> 0
C55: 22 00 00 | D55: Plumbing | E55: =Estimate!N932+Estimate!N968 -> 0 | F55: =IF($E$6=0,0,E55/$E$6) -> 0
C56: 23 00 00 | D56: HVAC | E56: =Estimate!N990+Estimate!N1016 -> 0 | F56: =IF($E$6=0,0,E56/$E$6) -> 0
C57: 26 00 00 | D57: Electrical | E57: =Estimate!N1043+Estimate!N1080+Estimate!N1128+Estimate!N1200 -> 33.99 | F57: =IF($E$6=0,0,E57/$E$6) -> 0
C58: 26 51 00 | D58: Interior Lighting | E58: =Estimate!N1107+Estimate!N1156 -> 1100 | F58: =IF($E$6=0,0,E58/$E$6) -> 0
C59: 26 56 00 | D59: Exterior Lighting | E59: =Estimate!N1066 -> 0 | F59: =IF($E$6=0,0,E59/$E$6) -> 0
C60: 27 00 00 | D60: Data/Comm Systems | E60: =Estimate!N1170 -> 0 | F60: =IF($E$6=0,0,E60/$E$6) -> 0
C61: 28 00 00 | D61: Security/Access Control Systems | E61: =Estimate!N1180 -> 0 | F61: =IF($E$6=0,0,E61/$E$6) -> 0
C62: 28 00 00 | D62: Fire Alarm | E62: =Estimate!N1192 -> 0 | F62: =IF($E$6=0,0,E62/$E$6) -> 0
D63: Subtotal - Building | E63: =SUM(E26:E62) -> 6183.99 | F63: =IF($E$6=0,0,E63/$E$6) -> 0 | G63: /BSF | L63: =IF(E63=Estimate!N328,"BLDG CHECKS","ERROR - CHECK SUMS") -> BLDG CHECKS | M63: =E63 -> 6183.99 | N63: =Estimate!N328 -> 6183.99 | O63: =M63-N63 -> 0
D65: Subtotal - Site & Building | E65: =E23+E63 -> 6183.99 | F65: =IF($E$6=0,0,E65/$E$6) -> 0 | G65: /BSF
B67: General Conditions & Fees | C67: 01 00 00 | D67: General Conditions | E67: =Estimate!N9+Estimate!N1211 -> 0 | F67: =IF($E$6=0,0,E67/$E$6) -> 0
C68: 01 20 00 | D68: General Liability Insurance | E68: =Estimate!M1243 -> 40.396915 | F68: =IF($E$6=0,0,E68/$E$6) -> 0
C69: 01 20 00 | D69: Builder's Risk Insurance | E69: =Estimate!M1244 -> 0 | F69: =IF($E$6=0,0,E69/$E$6) -> 0 | I69: Allowance
C70: 01 20 00 | D70: Design & Testing | E70: =Estimate!N1220 -> 0 | F70: =IF($E$6=0,0,E70/$E$6) -> 0
C71: 01 20 00 | D71: Permits | E71: =Estimate!N1232 -> 0 | F71: =IF($E$6=0,0,E71/$E$6) -> 0
C72: 01 20 00 | D72: Sub Bonds | E72: =Estimate!N1215 -> 30.91995 | F72: =IF($E$6=0,0,E72/$E$6) -> 0
C73: 01 20 00 | D73: Overhead & Profit | E73: =Estimate!N1248 -> 312.76534 | F73: =IF($E$6=0,0,E73/$E$6) -> 0
D74: Subtotal - GC's & Fees | E74: =SUM(E67:E73) -> 384.08221 | F74: =IF($E$6=0,0,E74/$E$6) -> 0 | G74: /BSF | L74: =IF(E74=Estimate!N1209+Estimate!N9,"GCs & FEE CHECKS","ERROR - CHECK SUMS") -> GCs & FEE CHECKS | M74: =E74 -> 384.08221 | N74: =Estimate!N1209+Estimate!N9 -> 384.08221 | O74: =M74-N74 -> 0
B76: Allowances | C76: 01 20 00 | D76: =Estimate!E1255 -> Landscaping & Irrigation | E76: =Estimate!J1255 -> 0 | F76: =IF($E$6=0,0,E76/$E$6) -> 0
C77: 01 20 00 | D77: =Estimate!E1256 -> Allowance #2 | E77: =Estimate!J1256 -> 0 | F77: =IF($E$6=0,0,E77/$E$6) -> 0
C78: 01 20 00 | D78: =Estimate!E1257 -> Allowance #3 | E78: =Estimate!J1257 -> 0 | F78: =IF($E$6=0,0,E78/$E$6) -> 0
C79: 01 20 00 | D79: =Estimate!E1258 -> Allowance #4 | E79: =Estimate!J1258 -> 0 | F79: =IF($E$6=0,0,E79/$E$6) -> 0
C80: 01 20 00 | D80: =Estimate!E1259 -> Allowance #5 | E80: =Estimate!J1259 -> 0 | F80: =IF($E$6=0,0,E80/$E$6) -> 0
C81: 01 20 00 | D81: =Estimate!E1260 -> Allowance #6 | E81: =Estimate!J1260 -> 0 | F81: =IF($E$6=0,0,E81/$E$6) -> 0
C82: 01 20 00 | D82: =Estimate!E1261 -> Allowance #7 | E82: =Estimate!J1261 -> 0 | F82: =IF($E$6=0,0,E82/$E$6) -> 0
C83: 01 20 00 | D83: =Estimate!E1262 -> Allowance #8 | E83: =Estimate!J1262 -> 0 | F83: =IF($E$6=0,0,E83/$E$6) -> 0
C84: 01 20 00 | D84: =Estimate!E1263 -> Allowance #9 | E84: =Estimate!J1263 -> 0 | F84: =IF($E$6=0,0,E84/$E$6) -> 0
C85: 01 20 00 | D85: =Estimate!E1264 -> Allowance #10 | E85: =Estimate!J1264 -> 0 | F85: =IF($E$6=0,0,E85/$E$6) -> 0
C86: 01 20 00 | D86: =Estimate!E1265 -> Allowance #11 | E86: =Estimate!J1265 -> 0 | F86: =IF($E$6=0,0,E86/$E$6) -> 0
C87: 01 20 00 | D87: =Estimate!E1266 -> Allowance #12 | E87: =Estimate!J1266 -> 0 | F87: =IF($E$6=0,0,E87/$E$6) -> 0
D88: Subtotal - Allowances | E88: =SUM(E76:E87) -> 0 | F88: =IF($E$6=0,0,E88/$E$6) -> 0 | G88: /BSF | L88: =IF(E88=Estimate!N1253,"ALLOWANCES CHECK","ERROR - CHECK SUMS") -> ALLOWANCES CHECK | M88: =E88 -> 0 | N88: =Estimate!N1253 -> 0 | O88: =M88-N88 -> 0
D90: PROJECT TOTAL | E90: =E65+E74+E88 -> 6568.0722 | F90: =IF($E$6=0,0,E90/$E$6) -> 0 | G90: /BSF | L90: =IF(E90=Estimate!N1269,"PROJECT TOTAL CHECKS","ERROR - CHECK SUMS") -> PROJECT TOTAL CHECKS | M90: =E90 -> 6568.0722 | N90: =Estimate!N1269 -> 6568.0722 | O90: =M90-N90 -> 0
B93: Alternates | C93: =Estimate!D1273 -> 1 | D93: =IF(Estimate!E1273="","",Estimate!E1273) -> Alternate No. 1 | E93: =IF(Estimate!I1273=0,"",Estimate!I1273) | F93: =Estimate!J1273
C94: =Estimate!D1274 | D94: =IF(Estimate!E1274="","",Estimate!E1274) | E94: =IF(Estimate!I1274=0,"",Estimate!I1274) | F94: =Estimate!J1274
C95: =Estimate!D1275 | D95: =IF(Estimate!E1275="","",Estimate!E1275) | E95: =IF(Estimate!I1275=0,"",Estimate!I1275) | F95: =Estimate!J1275
C96: =Estimate!D1276 | D96: =IF(Estimate!E1276="","",Estimate!E1276) | E96: =IF(Estimate!I1276=0,"",Estimate!I1276) | F96: =Estimate!J1276
C97: =Estimate!D1277 | D97: =IF(Estimate!E1277="","",Estimate!E1277) | E97: =IF(Estimate!I1277=0,"",Estimate!I1277) | F97: =Estimate!J1277
C98: =Estimate!D1278 | D98: =IF(Estimate!E1278="","",Estimate!E1278) | E98: =IF(Estimate!I1278=0,"",Estimate!I1278) | F98: =Estimate!J1278
C99: =Estimate!D1279 | D99: =IF(Estimate!E1279="","",Estimate!E1279) | E99: =IF(Estimate!I1279=0,"",Estimate!I1279) | F99: =Estimate!J1279
C100: =Estimate!D1280 | D100: =IF(Estimate!E1280="","",Estimate!E1280) | E100: =IF(Estimate!I1280=0,"",Estimate!I1280) | F100: =Estimate!J1280
C101: =Estimate!D1281 | D101: =IF(Estimate!E1281="","",Estimate!E1281) | E101: =IF(Estimate!I1281=0,"",Estimate!I1281) | F101: =Estimate!J1281
C102: =Estimate!D1282 | D102: =IF(Estimate!E1282="","",Estimate!E1282) | E102: =IF(Estimate!I1282=0,"",Estimate!I1282)
C103: =Estimate!D1283 | D103: =IF(Estimate!E1283="","",Estimate!E1283) | E103: =IF(Estimate!I1283=0,"",Estimate!I1283)
C104: =Estimate!D1284 | D104: =IF(Estimate!E1284="","",Estimate!E1284) | E104: =IF(Estimate!I1284=0,"",Estimate!I1284)
C105: =Estimate!D1285 | D105: =IF(Estimate!E1285="","",Estimate!E1285) | E105: =IF(Estimate!I1285=0,"",Estimate!I1285)

Sheet Estimate
E1: estimate checks | F1: =IF(SUM(U9:U1270)=0,"GOOD TO GO","") -> GOOD TO GO | G1: =IF(SUM(U9:U1270)=0,"","UH OH, YOU MESSED UP")
F2: Client: | G2: =+'Project Info Input'!C11 -> 0 | I2: =+N1269 -> 6568.0722 | J2: Grand Total | Q2: Site | R2: ='Budget Summary'!E23 -> 0 | S2: =IFERROR(R2/$G$6,0) -> 0
F3: Project Name: | G3: ='Project Info Input'!C8 -> Test | I3: =O1269 -> 0 | J3: /BSF | Q3: Building | R3: ='Budget Summary'!E63 -> 6183.99 | S3: =IFERROR(R3/$G$6,0) -> 0
F4: Location: | G4: ='Project Info Input'!C10 -> Test 1 | I4: ='Project Info Input'!C31 -> 0 | J4: Clear Height | Q4: GC's and Fees | R4: ='Budget Summary'!E74 -> 384.08221 | S4: =IFERROR(R4/$G$6,0) -> 0
F5: Date: | G5: ='Budget Summary'!E5 -> 0 | I5: =G6/(G7*43560) -> #DIV/0! | J5: Bldg Footprint to Site Ratio | Q5: Allowances | R5: ='Budget Summary'!E88 -> 0 | S5: =IFERROR(R5/$G$6,0) -> 0
F6: Building Size (SF): | G6: ='Project Info Input'!C43 -> 0 | I6: =G392/G6 -> #DIV/0! | J6: Wall to Floor Ratio
F7: Size (Acres): | G7: ='Project Info Input'!C28 -> 0 | I7: =(SUM(G202:G206)+(SUM(G236:G239)*9))/G6 -> #DIV/0! | J7: Pvg to Floor Ratio | Q7: ESTIMATE CHECK FORMULAS ENTERED BELOW IN THESE COLUMNS
A8: Filter | B8: Bid Form Mapping | C8: Subcontractor Name | D8: CSI | E8: Work Description | F8: Details | G8: Quantity | H8: Unit | I8: $/Unit | J8: Cntrl Est Line Item Total | K8: INC | L8: SUB QUOTE | M8: BUDGET | N8: Grand Total | O8: $/SF
A9: x | E9: GENERAL CONDITIONS | G9: =SUM(G10:G12) -> 0 | H9: MOS | I9: =N9/G9 -> #DIV/0! | N9: =SUM(N10:N21) -> 0 | O9: =IFERROR(N9/$G$6,0) -> 0 | Q9: =IF(SUM(M10:M21)=SUM(N10:N21),"SUBTOTALS MATCH LINE ITEM TOTALS","ERROR- CHECK SUMS") -> SUBTOTALS MATCH LINE ITEM TOTALS | S9: =SUM(M10:M21) -> 0 | T9: =SUM(N10:N21) -> 0 | U9: =S9-T9 -> 0
A10: x | D10: 01 | E10: GENERAL CONDITIONS | N10: =SUM(M10:M13) -> 0 | O10: =IFERROR(N10/$G$6,0) -> 0 | Q10: =IF(SUM(M10:M21)=N9,"DIVISION TOTAL MATCHES LINE ITEM TOTALS","ERROR- CHECK SUMS") -> DIVISION TOTAL MATCHES LINE ITEM TOTALS | S10: =SUM(M10:M21) -> 0 | T10: =N9 -> 0 | U10: =S10-T10 -> 0
A11: x | D11: 01 00 00 | E11: Site GCs | G11: ='Project Info Input'!C22 -> 0 | H11: MO | I11: ='General Conditions'!H129 -> 0 | J11: =G11*I11 -> 0 | M11: =IF(K11="x","Included in Sub Bid",J11) -> 0 | Q11: =IF(N9=SUM(N10:N21),"DIVISION TOTAL MATCHES SUBTOTALS","ERROR- SUBTOTALS") -> DIVISION TOTAL MATCHES SUBTOTALS | S11: =N9 -> 0 | T11: =SUM(N10:N21) -> 0 | U11: =S11-T11 -> 0
A12: x | D12: 01 00 00 | E12: Building GCs | G12: ='Project Info Input'!C23 -> 0 | H12: MO | I12: ='General Conditions'!H129 -> 0 | J12: =G12*I12 -> 0 | M12: =IF(K12="x","Included in Sub Bid",J12) -> 0
A13: x | D13: 01 00 00 | E13: Closeout GCs | G13: ='Project Info Input'!C24 -> 0.5 | H13: MO | I13: =I11/2 -> 0 | J13: =G13*I13 -> 0 | M13: =IF(K13="x","Included in Sub Bid",J13) -> 0
A14: x | D14: 01 | E14: MOBILIZATION | N14: =SUM(M15:M16) -> 0 | O14: =IFERROR(N14/$G$6,0) -> 0
A15: x | D15: 01 00 00 | E15: Mobilization | G15: 1 | H15: LS | J15: =G15*I15 -> 0 | M15: =IF(K15="x","Included in Sub Bid",J15) -> 0
A16: x | D16: 01 00 00 | E16: Web Cam | H16: MO | I16: 600 | J16: =G16*I16 -> 0 | M16: =IF(K16="x","Included in Sub Bid",J16) -> 0
A17: x | D17: 01 | E17: FINAL CLEANING | N17: =SUM(M18:M21) -> 0 | O17: =IFERROR(N17/$G$6,0) -> 0
A18: x | D18: 01 00 00 | E18: Warehouse | G18: ='Project Info Input'!C34-Estimate!G19 -> 0 | H18: SF | I18: 0.05 | J18: =G18*I18 -> 0 | M18: =IF(K18="x","Included in Sub Bid",J18) -> 0
A19: x | D19: 01 00 00 | E19: Office | G19: ='Project Info Input'!C38 -> 0 | H19: SF | I19: 0.35 | J19: =G19*I19 -> 0 | M19: =IF(K19="x","Included in Sub Bid",J19) -> 0
A20: x
A21: x
A22: =IF(J22=0,"Exclude","x") -> Exclude | E22: SITEWORK | J22: =SUBTOTAL(9,J23:J327) -> 0 | K22: =IFERROR(J22/$G$6,0) -> 0 | N22: =SUM(N23:N327) -> 0 | O22: =IFERROR(N22/$G$6,0) -> 0 | Q22: =IF(SUM(M23:M327)=SUM(N23:N327),"SUBTOTALS MATCH LINE ITEM TOTALS","ERROR- CHECK SUMS") -> SUBTOTALS MATCH LINE ITEM TOTALS | S22: =SUM(M23:M327) -> 0 | T22: =SUM(N23:N327) -> 0 | U22: =S22-T22 -> 0
A23: =IF(J23=0,"Exclude","x") -> Exclude | D23: 02 | E23: DEMOLITION | J23: =SUBTOTAL(9,J24:J38) -> 0 | K23: =IFERROR(J23/$G$6,0) -> 0 | N23: =SUM(M24:M38) -> 0 | O23: =IFERROR(N23/$G$6,0) -> 0 | Q23: =IF(SUM(M23:M327)=N22,"DIVISION TOTAL MATCHES LINE ITEM TOTALS","ERROR- CHECK SUMS") -> DIVISION TOTAL MATCHES LINE ITEM TOTALS | S23: =SUM(M23:M327) -> 0 | T23: =N22 -> 0 | U23: =S23-T23 -> 0
A24: =A23 -> Exclude | D24: 02 40 00 | E24: Sub Bid | L24: 0 | M24: =L24 -> 0
A25: =A24 -> Exclude | D25: 02 40 00 | E25: Walls | H25: LF | J25: =G25*I25 -> 0 | M25: =IF(K25="x","Included in Sub Bid",J25) -> 0 | Q25: =IF(N22=SUM(N23:N327),"DIVISION TOTAL MATCHES SUBTOTALS","ERROR- SUBTOTALS") -> DIVISION TOTAL MATCHES SUBTOTALS | S25: =N22 -> 0 | T25: =SUM(N23:N327) -> 0 | U25: =S25-T25 -> 0
A26: =A25 -> Exclude | D26: 02 40 00 | E26: Doors | H26: EA | I26: 3500 | J26: =G26*I26 -> 0 | M26: =IF(K26="x","Included in Sub Bid",J26) -> 0
A27: =A26 -> Exclude | D27: 02 40 00 | E27: Flooring | H27: SF | I27: 48 | J27: =G27*I27 -> 0 | M27: =IF(K27="x","Included in Sub Bid",J27) -> 0
A28: =A27 -> Exclude | D28: 02 40 00 | E28: Ceilings | H28: SF | I28: 400 | J28: =G28*I28 -> 0 | M28: =IF(K28="x","Included in Sub Bid",J28) -> 0
A29: =A28 -> Exclude | D29: 02 40 00 | E29: Masonry | H29: SF | I29: 550 | J29: =G29*I29 -> 0 | M29: =IF(K29="x","Included in Sub Bid",J29) -> 0
A30: =A29 -> Exclude | D30: 02 40 00 | E30: Cut openings in existing panels | H30: EA | J30: =G30*I30 -> 0 | M30: =IF(K30="x","Included in Sub Bid",J30) -> 0
A31: =A30 -> Exclude | D31: 02 40 00 | E31: Asphalt | H31: SF | J31: =G31*I31 -> 0 | M31: =IF(K31="x","Included in Sub Bid",J31) -> 0
A32: =A31 -> Exclude | D32: 02 40 00 | E32: Curb Cut | H32: EA | I32: 3500 | J32: =G32*I32 -> 0 | M32: =IF(K32="x","Included in Sub Bid",J32) -> 0
A33: =A32 -> Exclude | D33: 02 40 00 | E33: Curb | H33: SF | J33: =G33*I33 -> 0 | M33: =IF(K33="x","Included in Sub Bid",J33) -> 0
A34: =A33 -> Exclude | D34: 02 40 00 | E34: Concrete Paving | H34: SF | J34: =G34*I34 -> 0 | M34: =IF(K34="x","Included in Sub Bid",J34) -> 0
A35: =A34 -> Exclude | D35: 02 40 00 | E35: Subcontractor Adjustment | H35: LS | M35: =IF(K35="x","Included in Sub Bid",G35*I35) -> 0
A36: =A35 -> Exclude | D36: 02 40 00 | E36: Bid Day Cut | H36: LS | M36: =IF(K36="x","Included in Sub Bid",G36*I36) -> 0
A37: =A36 -> Exclude
A38: =A37 -> Exclude
A39: =IF(J39=0,"Exclude","x") -> Exclude | D39: 31 | E39: EROSION CONTROL | J39: =SUBTOTAL(9,J40:J54) -> 0 | K39: =IFERROR(J39/$G$6,0) -> 0 | N39: =SUM(M40:M54) -> 0 | O39: =IFERROR(N39/$G$6,0) -> 0
A40: =A39 -> Exclude | D40: 31 25 00 | E40: Sub Bid | L40: 0 | M40: =L40 -> 0
A41: =A40 -> Exclude | D41: 31 25 00 | E41: Erosion Control | G41: =$G$7 -> 0 | H41: AC | I41: 2500 | J41: =I41*G41 -> 0 | M41: =IF(K41="x","Included in Sub Bid",J41) -> 0
A42: =A41 -> Exclude | D42: 31 25 00 | E42: Construction Entrance | H42: EA | I42: 2000 | J42: =G42*I42 -> 0 | M42: =IF(K42="x","Included in Sub Bid",J42) -> 0
A43: =A42 -> Exclude | D43: 31 25 00 | E43: Silt Fence - Install | H43: LF | I43: 2 | J43: =G43*I43 -> 0 | M43: =IF(K43="x","Included in Sub Bid",J43) -> 0
A44: =A43 -> Exclude | D44: 31 25 00 | E44: Silt Fence - Removal | H44: LF | I44: 1 | J44: =G44*I44 -> 0 | M44: =IF(K44="x","Included in Sub Bid",J44) -> 0
A45: =A44 -> Exclude | D45: 31 25 00 | E45: SWPPP Plan | H45: LS | I45: 1500 | J45: =G45*I45 -> 0 | M45: =IF(K45="x","Included in Sub Bid",J45) -> 0
A46: =A45 -> Exclude | D46: 31 25 00 | E46: SWPPP Inspections | H46: WK | I46: 250 | J46: =G46*I46 -> 0 | M46: =IF(K46="x","Included in Sub Bid",J46) -> 0
A47: =A46 -> Exclude | D47: 31 25 00 | E47: Additional Rock | H47: SF | I47: 1.25 | J47: =G47*I47 -> 0 | M47: =IF(K47="x","Included in Sub Bid",J47) -> 0
A48: =A47 -> Exclude | D48: 31 25 00 | E48: Rock Check Dam | H48: EA | I48: 2500 | J48: =G48*I48 -> 0 | M48: =IF(K48="x","Included in Sub Bid",J48) -> 0
A49: =A48 -> Exclude | D49: 31 25 00 | E49: Inlet Protection | H49: EA | I49: 250 | J49: =G49*I49 -> 0 | M49: =IF(K49="x","Included in Sub Bid",J49) -> 0
A50: =A49 -> Exclude | D50: 31 25 00 | E50: Street Maintenance | H50: MNTH | I50: 2000 | J50: =G50*I50 -> 0 | M50: =IF(K50="x","Included in Sub Bid",J50) -> 0
A51: =A50 -> Exclude | D51: 31 25 00 | E51: Subcontractor Adjustment | H51: LS | M51: =IF(K51="x","Included in Sub Bid",G51*I51) -> 0
A52: =A51 -> Exclude | D52: 31 25 00 | E52: Bid Day Cut | H52: LS | M52: =IF(K52="x","Included in Sub Bid",G52*I52) -> 0
A53: =A52 -> Exclude
A54: =A53 -> Exclude
A55: =IF(J55=0,"Exclude","x") -> Exclude | D55: 31 | E55: EARTHWORK | J55: =SUBTOTAL(9,J56:J95) -> 0 | K55: =IFERROR(J55/$G$6,0) -> 0 | N55: =SUM(M56:M95) -> 0 | O55: =IFERROR(N55/$G$6,0) -> 0
A56: =A55 -> Exclude | D56: 31 00 00 | E56: Sub Bid - EARTHWORK | L56: 0 | M56: =L56 -> 0
A57: =A56 -> Exclude | D57: 31 00 00 | E57: Sub Bid - STONE BASE | L57: 0 | M57: =L57 -> 0
A58: =A57 -> Exclude | D58: 31 00 00 | E58: Mobilize | H58: LS | I58: 10000 | J58: =G58*I58 -> 0 | M58: =IF(K58="x","Included in Sub Bid",J58) -> 0
A59: =A58 -> Exclude | D59: 31 00 00 | E59: Staking/Layout | G59: =G7 -> 0 | H59: AC | I59: 1500 | J59: =I59*G59 -> 0 | M59: =IF(K59="x","Included in Sub Bid",J59) -> 0
A60: =A59 -> Exclude | D60: 31 00 00 | E60: Site Clearing-Chip and Haul | H60: AC | I60: 5000 | J60: =I60*G60 -> 0 | M60: =IF(K60="x","Included in Sub Bid",J60) -> 0
A61: =A60 -> Exclude | D61: 31 00 00 | E61: Strip Topsoil & Respread | F61: 0.5 | G61: =G7*43560*F61/27 -> 0 | H61: CY | I61: 2 | J61: =I61*G61 -> 0 | M61: =IF(K61="x","Included in Sub Bid",J61) -> 0
A62: =A61 -> Exclude | D62: 31 00 00 | E62: Strip Topsoil & Haul Off | H62: CY | I62: 10 | J62: =I62*G62 -> 0 | M62: =IF(K62="x","Included in Sub Bid",J62) -> 0
A63: =A62 -> Exclude | D63: 31 00 00 | E63: Mass Grade Cut/Fill | F63: 10000 | G63: =G7*F63 -> 0 | H63: CY | I63: 2.65 | J63: =I63*G63 -> 0 | M63: =IF(K63="x","Included in Sub Bid",J63) -> 0
A64: =A63 -> Exclude | D64: 31 00 00 | E64: Import Fill Material | H64: CY | I64: 15 | J64: =I64*G64 -> 0 | M64: =IF(K64="x","Included in Sub Bid",J64) -> 0
A65: =A64 -> Exclude | D65: 31 00 00 | E65: Export Excess Material | H65: CY | I65: 10 | J65: =I65*G65 -> 0 | M65: =IF(K65="x","Included in Sub Bid",J65) -> 0
A66: =A65 -> Exclude | D66: 31 00 00 | E66: Fine Grading | G66: =G7 -> 0 | H66: AC | I66: 3500 | J66: =I66*G66 -> 0 | M66: =IF(K66="x","Included in Sub Bid",J66) -> 0
A67: =A66 -> Exclude | D67: 31 00 00 | E67: Fine Grading - Building Pad | G67: =G6/9 -> 0 | H67: SY | I67: 1.75 | J67: =I67*G67 -> 0 | M67: =IF(K67="x","Included in Sub Bid",J67) -> 0
A68: =A67 -> Exclude | D68: 31 00 00 | E68: Fine Grading - Paving Areas | H68: SY | I68: 1.75 | J68: =I68*G68 -> 0 | M68: =IF(K68="x","Included in Sub Bid",J68) -> 0
A69: =A68 -> Exclude | D69: 31 00 00 | E69: Fine Grading - Dolly Pads | H69: SY | I69: 3 | J69: =I69*G69 -> 0 | M69: =IF(K69="x","Included in Sub Bid",J69) -> 0
A70: =A69 -> Exclude | D70: 31 00 00 | E70: Fine Grading - Curb & Gutter | H70: SY | I70: 1.75 | J70: =I70*G70 -> 0 | M70: =IF(K70="x","Included in Sub Bid",J70) -> 0
A71: =A70 -> Exclude | D71: 31 00 00 | E71: Fine Grading - Green Spaces | H71: SY | I71: 0.44 | J71: =I71*G71 -> 0 | M71: =IF(K71="x","Included in Sub Bid",J71) -> 0
A72: =A71 -> Exclude | D72: 31 00 00 | E72: Detention Pond Excavation | H72: CY | I72: 2.75 | J72: =I72*G72 -> 0 | M72: =IF(K72="x","Included in Sub Bid",J72) -> 0
A73: =A72 -> Exclude | D73: 31 00 00 | E73: Detention Pond Demucking & Hauloff | H73: CY | J73: =I73*G73 -> 0 | M73: =IF(K73="x","Included in Sub Bid",J73) -> 0
A74: =A73 -> Exclude | D74: 31 00 00 | E74: Surcharge | H74: CY | J74: =I74*G74 -> 0 | M74: =IF(K74="x","Included in Sub Bid",J74) -> 0
A75: =A74 -> Exclude | D75: 31 00 00 | E75: Bldg Cap - Stone | F75: 4 | G75: =G6*1.03/9*F75*110/2000 -> 0 | H75: TONS | I75: 32 | J75: =I75*G75 -> 0 | M75: =IF(K75="x","Included in Sub Bid",J75) -> 0
A76: =A75 -> Exclude | D76: 31 00 00 | E76: Bldg Cap - Select Fill | H76: CY | I76: 15 | J76: =I76*G76 -> 0 | M76: =IF(K76="x","Included in Sub Bid",J76) -> 0
A77: =A76 -> Exclude | D77: 31 00 00 | E77: Bldg Cap - Cement Stabilization | H77: SY | I77: 8 | J77: =I77*G77 -> 0 | M77: =IF(K77="x","Included in Sub Bid",J77) -> 0
A78: =A77 -> Exclude | D78: 31 00 00 | E78: Bldg Cap - Lime Stabilization | H78: SY | I78: 5.2 | J78: =I78*G78 -> 0 | M78: =IF(K78="x","Included in Sub Bid",J78) -> 0
A79: =A78 -> Exclude | D79: 31 00 00 | E79: Building Pad - Moisture Condition | H79: CY | I79: 2.65 | J79: =I79*G79 -> 0 | M79: =IF(K79="x","Included in Sub Bid",J79) -> 0
A80: =A79 -> Exclude | D80: 31 00 00 | E80: Water & Water Meter for Earthwork | F80: for bldg pad MC | G80: =IF(G79=0,0,1) -> 0 | H80: LS | I80: 45000 | J80: =I80*G80 -> 0 | M80: =IF(K80="x","Included in Sub Bid",J80) -> 0
A81: =A80 -> Exclude | D81: 31 00 00 | E81: Rip Rock | H81: CY | I81: 3 | J81: =I81*G81 -> 0 | M81: =IF(K81="x","Included in Sub Bid",J81) -> 0
A82: =A81 -> Exclude | D82: 31 00 00 | E82: Blast Rock | H82: CY | I82: 16 | J82: =I82*G82 -> 0 | M82: =IF(K82="x","Included in Sub Bid",J82) -> 0
A83: =A82 -> Exclude | D83: 31 00 00 | E83: Trench Rock | H83: CY | I83: 75 | J83: =I83*G83 -> 0 | M83: =IF(K83="x","Included in Sub Bid",J83) -> 0
A84: =A83 -> Exclude | D84: 31 00 00 | E84: Temp Seeding | H84: SF | I84: 0.12 | J84: =I84*G84 -> 0 | M84: =IF(K84="x","Included in Sub Bid",J84) -> 0
A85: =A84 -> Exclude | D85: 31 00 00 | E85: Permanent Seeding | H85: SF | I85: 0.16 | J85: =I85*G85 -> 0 | M85: =IF(K85="x","Included in Sub Bid",J85) -> 0
A86: =A85 -> Exclude | D86: 31 00 00 | E86: Backfill Curb & Gutter | G86: =SUM(G218:G221) -> 0 | H86: LF | I86: 2.5 | J86: =I86*G86 -> 0 | M86: =IF(K86="x","Included in Sub Bid",J86) -> 0
A87: =A86 -> Exclude | D87: 32 13 13 | E87: Concrete Pavement - Stone Base | F87: 6 | G87: =SUM(G202:G206)*1.03/9*F87*110/2000 -> 0 | H87: TONS | I87: 32 | J87: =G87*I87 -> 0 | M87: =IF(K87="x","Included in Sub Bid",J87) -> 0
A88: =A87 -> Exclude | D88: 31 00 00 | E88: Pavement Subgrade - Cement Stabilize | H88: SY | I88: 6.2 | J88: =I88*G88 -> 0 | M88: =IF(K88="x","Included in Sub Bid",J88) -> 0
A89: =A88 -> Exclude | D89: 31 00 00 | E89: Pavement Subgrade - Lime Stabilize | H89: SY | I89: 5.6 | J89: =I89*G89 -> 0 | M89: =IF(K89="x","Included in Sub Bid",J89) -> 0
A90: =A89 -> Exclude | D90: 31 00 00 | E90: Laydown/Trailer Yard incl Fabric & Removal | G90: =IF(SUM(G58:G89)=0,0,1) -> 0 | H90: LS | I90: 10000 | J90: =I90*G90 -> 0 | M90: =IF(K90="x","Included in Sub Bid",J90) -> 0
A91: =A90 -> Exclude | D91: 31 00 00 | E91: Temporary Roads | H91: TONS | I91: 36 | J91: =I91*G91 -> 0 | M91: =IF(K91="x","Included in Sub Bid",J91) -> 0
A92: =A91 -> Exclude | D92: 31 00 00 | E92: Subcontractor Adjustment | H92: LS | M92: =IF(K92="x","Included in Sub Bid",G92*I92) -> 0
A93: =A92 -> Exclude | D93: 31 00 00 | E93: Bid Day Cut | H93: LS | M93: =IF(K93="x","Included in Sub Bid",G93*I93) -> 0
A94: =A93 -> Exclude
A95: =A94 -> Exclude
A96: =IF(J96=0,"Exclude","x") -> Exclude | D96: 33 | E96: STORM SEWER | J96: =SUBTOTAL(9,J97:J141) -> 0 | K96: =IFERROR(J96/$G$6,0) -> 0 | N96: =SUM(M97:M141) -> 0 | O96: =IFERROR(N96/$G$6,0) -> 0
A97: =A96 -> Exclude | D97: 33 40 00 | E97: Sub Bid | L97: 0 | M97: =L97 -> 0
A98: =A97 -> Exclude | D98: 33 40 00 | E98: Roof Drain Leaders | H98: LF | I98: 40 | J98: =I98*G98 -> 0 | M98: =IF(K98="x","Included in Sub Bid",J98) -> 0
A99: =A98 -> Exclude | D99: 33 40 00 | E99: Gutter to Roof Drain Transitions | H99: EA | I99: 250 | J99: =I99*G99 -> 0 | M99: =IF(K99="x","Included in Sub Bid",J99) -> 0
A100: =A99 -> Exclude | D100: 33 40 00 | E100: Storm Pipe | H100: LF | J100: =I100*G100 -> 0 | M100: =IF(K100="x","Included in Sub Bid",J100) -> 0
...

Sheet Clarifications
E3: Clarifications
E4: ='Project Info Input'!C8 -> Test
E5: ='Project Info Input'!C10 -> Test 1
E6: ='Project Info Input'!C15 -> 0
A8: GENERAL
A9: 1 | B9: Estimate is based on the following:
B10: a. | C10: Plans prepared by XX dated XX
B11: b. | C11: Specifications prepared by XX dated XX
B12: c. | C12: Geotechnical Report prepared by XX dated XX
A13: 2 | B13: Pricing is based on a | E13: ='Project Info Input'!C25 -> 0 | F13: month construction schedule.
A14: 3 | B14: Pricing is good for thirty (30) days.
A15: 4 | B15: Design is included/excluded (move to exclusions if excluded).
B16: Civil -
B17: Structural -
B18: Architectural -
B19: MEP/F - Design Build
A20: 5 | B20: Builders Risk Insurance is included/excluded/

Sheet GCs Input, Staff & IT Costs
B2: GCs INPUT | I2: STAFFING RATES
I3: Position | J3: Avg Sal | K3: Monthly Rate | L3: Hourly Rate | M3: New Rate | N3: Old Rate | O3: Old Salary
B4: Project Name | C4: ='Project Info Input'!C8 -> Test | I4: Project Executive | J4: 170000 | K4: =+J4/12 -> 14166.667 | L4: =+J4/2080 -> 81.730769 | M4: =+L4*1.4 -> 114.42308 | P4: Yes
B5: Start Date | C5: ='Project Info Input'!C19 -> 0 | I5: Senior Project Manager | J5: 142000 | K5: =+J5/12 -> 11833.333 | L5: =+J5/2080 -> 68.269231 | M5: =+L5*1.4 -> 95.576923 | N5: 125 | O5: =N5*2080/1.4 -> 185714.29 | P5: No
B6: Project Length (mos) | C6: ='Project Info Input'!C25 -> 0 | I6: Project Manager | J6: 120000 | K6: =+J6/12 -> 10000 | L6: =+J6/2080 -> 57.692308 | M6: =+L6*1.4 -> 80.769231 | N6: 105 | O6: =N6*2080/1.4 -> 156000
I7: Assistant Project Manager | J7: 85000 | K7: =+J7/12 -> 7083.3333 | L7: =+J7/2080 -> 40.865385 | M7: =+L7*1.4 -> 57.211538 | N7: 65 | O7: =N7*2080/1.4 -> 96571.429
B8: Personnel | C8: Needed | D8: Months | E8: % | F8: Monthly Rate | I8: Assistant Project Manager | J8: 85000 | K8: =+J8/12 -> 7083.3333 | L8: =+J8/2080 -> 40.865385 | M8: =+L8*1.4 -> 57.211538 | N8: 65 | O8: =N8*2080/1.4 -> 96571.429
I9: Project Engineer | J9: 55000 | K9: =+J9/12 -> 4583.3333 | L9: =+J9/2080 -> 26.442308 | M9: =+L9*1.4 -> 37.019231 | O9: =N9*2080/1.4 -> 0
B10: Preconstruction | C10: FALSE | D10: Flat fee | E10: Flat fee | F10: 1000 | I10: Project Coordinator | J10: 81000 | K10: =+J10/12 -> 6750 | L10: =+J10/2080 -> 38.942308 | M10: =+L10*1.4 -> 54.519231 | N10: 55 | O10: =N10*2080/1.4 -> 81714.286
B11: General Super | C11: FALSE | D11: =+$C$6 -> 0 | E11: Flat fee | F11: =750/2 -> 375 | I11: Senior Superintendent | J11: 135000 | K11: =+J11/12 -> 11250 | L11: =+J11/2080 -> 64.903846 | M11: =+L11*1.4 -> 90.865385 | N11: 95 | O11: =N11*2080/1.4 -> 141142.86
B12: Safety Manager | C12: FALSE | D12: =+$C$6 -> 0 | E12: Flat fee | F12: 750 | I12: Superintendent | J12: 120000 | K12: =+J12/12 -> 10000 | L12: =+J12/2080 -> 57.692308 | M12: =+L12*1.4 -> 80.769231 | N12: 95 | O12: =N12*2080/1.4 -> 141142.86
B13: Compliance | C13: FALSE | D13: =+$C$6 -> 0 | E13: Flat fee | F13: =750/2 -> 375 | I13: Assistant Superintedent | J13: 85000 | K13: =+J13/12 -> 7083.3333 | L13: =+J13/2080 -> 40.865385 | M13: =+L13*1.4 -> 57.211538 | N13: 65 | O13: =N13*2080/1.4 -> 96571.429
B14: Project Executive | C14: FALSE | D14: =+$C$6 -> 0 | E14: 0.5 | F14: =+'GCs Input, Staff & IT Costs'!K4 -> 14166.667 | I14: Assistant Superintedent | J14: 85000 | K14: =+J14/12 -> 7083.3333 | L14: =+J14/2080 -> 40.865385 | M14: =+L14*1.4 -> 57.211538 | N14: 65 | O14: =N14*2080/1.4 -> 96571.429
I15: Safety Manager | J15: 130000 | K15: =(J15/12)/35 -> 309.52381 | L15: =+J15/2080 -> 62.5 | M15: =+L15*1.4 -> 87.5 | N15: 125 | O15: =N15*2080/1.4 -> 185714.29
B16: On-Site Safety | C16: FALSE | D16: =+$C$6 -> 0 | E16: 1 | F16: =+'GCs Input, Staff & IT Costs'!K18 -> 7916.6667 | I16: Compliance | J16: 200000 | K16: =(J16/12)/35 -> 476.19048 | L16: =+J16/2080 -> 96.153846 | M16: =+L16*1.4 -> 134.61538 | N16: 145 | O16: =N16*2080/1.4 -> 215428.57
I17: Accounting | J17: 74000 | K17: =+J17/12 -> 6166.6667 | L17: =+J17/2080 -> 35.576923 | M17: =+L17*1.4 -> 49.807692 | N17: 50 | O17: =N17*2080/1.4 -> 74285.714
B18: Senior Project Manager | C18: FALSE | D18: =+$C$6 -> 0 | E18: 0.5 | F18: =+'GCs Input, Staff & IT Costs'!K5 -> 11833.333 | I18: On-Site Safety | J18: 95000 | K18: =+J18/12 -> 7916.6667 | L18: =+J18/2080 -> 45.673077 | M18: =+L18*1.4 -> 63.942308 | N18: 75 | O18: =N18*2080/1.4 -> 111428.57
B19: Project Manager | C19: FALSE | D19: =+$C$6 -> 0 | E19: 0.33 | F19: =+'GCs Input, Staff & IT Costs'!K6 -> 10000 | I19: General Superintendent | J19: 175000 | K19: =(J19/12)/35 -> 416.66667 | L19: =+J19/2080 -> 84.134615 | M19: =+L19*1.4 -> 117.78846 | N19: 135 | O19: =N19*2080/1.4 -> 200571.43
B20: Assistant Project Manager | C20: FALSE | D20: =+$C$6 -> 0 | E20: 0.33 | F20: =+'GCs Input, Staff & IT Costs'!K7 -> 7083.3333
B21: Assistant Project Manager | C21: FALSE | D21: =+$C$6 -> 0 | E21: 0.33 | F21: =+'GCs Input, Staff & IT Costs'!K8 -> 7083.3333
I22: IT COSTS
B23: Senior Superintendent | C23: FALSE | D23: =+$C$6 -> 0 | E23: 1 | F23: =+'GCs Input, Staff & IT Costs'!K11 -> 11250 | I23: IT Support Cost | J23: 55.56 | K23: IT Salary X 2 to account for all expenses with half for corporate use and half for user support. Divided by number of users, divided by 12
B24: Superintendent | C24: FALSE | D24: =+$C$6 -> 0 | E24: 1 | F24: =+'GCs Input, Staff & IT Costs'!K12 -> 10000 | I24: Desktop Management software | J24: 4.58 | K24: $55 per year, divided by 12 months
B25: Assistant Superintendent | C25: FALSE | D25: =+$C$6 -> 0 | E25: 0.33 | F25: =+'GCs Input, Staff & IT Costs'!K13 -> 7083.3333 | I25: Antivirus | J25: 5.23 | K25: TrendMicro Worry Free Service for Business + DeepArmor
B26: Assistant Superintendent | C26: FALSE | D26: =+$C$6 -> 0 | E26: 1 | F26: =+'GCs Input, Staff & IT Costs'!K14 -> 7083.3333 | I26: Laptop | J26: 41.67 | K26: $1500 divided by 36 months
I27: Microsoft Office 365 | J27: 27 | K27: Includes a portion of Project used by PMs, APMs, and PCs
B28: Field Clerk | C28: FALSE | D28: =+$C$6 -> 0 | E28: 0.4 | F28: 1000 | I28: Mifi | J28: 58.58
B29: Project Coordinator | C29: FALSE | D29: =+$C$6 -> 0 | E29: 0.3 | F29: =+'GCs Input, Staff & IT Costs'!K10 -> 6750 | I29: Vista Viewpoint | J29: 38.88
B30: Accounting | C30: FALSE | D30: =+$C$6 -> 0 | E30: 0.3 | F30: =+'GCs Input, Staff & IT Costs'!K17 -> 6166.6667 | I30: Firewall | J30: 8.68 | K30: 1\2 of our $25,000py Frirewall spending (1/2 corp burden) divided by 12 months, spread over 100 users
B31: Scheduling Consultant | C31: FALSE | D31: =+$C$6 -> 0 | E31: 0.4 | F31: 3500 | I31: Security Cost | J31: 4.17 | K31: Penitration and hacking vulnerability testing per month spread over 100 users
B32: Temporary Labor | C32: FALSE | D32: =+$C$6 -> 0 | E32: 0.35 | F32: 1000 | I32: Total | J32: =SUM(J23:J31) -> 244.35
J33: 250 | K33: includes server upgrade and new cloud services
B34: Costs | C34: Flat Cost
B36: Vehicle | C36: 875
B37: Fuel | C37: 400
B38: Phone | C38: 150
B39: Travel & Per Diem | C39: 860
B40: Temporary Housing? | C40: TRUE | S40: Yes
B41: On-Site Safety | C41: =IF($C$40=TRUE,1500,0) -> 1500 | S41: No
B42: Senior PM | C42: =IF($C$40=TRUE,2500,0) -> 2500
B43: Project Manager | C43: =IF($C$40=TRUE,2500,0) -> 2500
B44: Assistant Project Manager | C44: =IF($C$40=TRUE,2200,0) -> 2200
B45: Senior Super | C45: =IF($C$40=TRUE,2500,0) -> 2500
B46: Superintendent | C46: =IF($C$40=TRUE,2500,0) -> 2500
B47: Assistant Superintendent | C47: =IF($C$40=TRUE,2200,0) -> 2200 | I47: ADD TRAILER PORCH TO ROUGH CARPENTRY
I48: ADD EQUIPMENT RENTAL TO EARTHWORK
B49: Field Office Rental | C49: 1500 | I49: REVISE CLOSEOUT TO 1 MONTH
B50: Field Office Setup | C50: 10000
B51: Temporary Water Installation | C51: 2500
B52: Temporary Water | C52: 250
B53: Temporary Toilets | C53: 800
B54: Temporary Power Installation | C54: 2000
B55: Temporary Power | C55: 350
B56: Temporary Generator | C56: 400
B58: Security Fence | C58: 4
B59: lineal feet qty
B60: Job Signs | C60: 4200
B61: Job Photos | C61: 150
B62: Office Supplies | C62: 250
B63: Printing | C63: 1500
B64: Postage/ Courier | C64: 250
B65: Misc. Tools & Equipment | C65: 500
B66: IT Costs | C66: 440 | D66: Adjusted 10/8/21 per Lee
B67: Dumpster Pulls | C67: 400
B68: per month | C68: 6
B69: General Clean-up | C69: 500

Sheet General Conditions
F2: ='GCs Input, Staff & IT Costs'!C4 -> Test | N2: SUMMARY
N3: =H129 -> 0 | O3: /Month
N4: ='Project Info Input'!C22+'Project Info Input'!C23 -> 0 | O4: Months
F5: General Conditions
P6: To hide rows,
P7: click on filter &
B8: Personnel | F8: % of Month | G8: # of Months | H8: Rate | I8: Burden Rate | J8: Monthly Rate | K8: Adjustments | L8: Total | P8: uncheck "remove"
P9: keep
B10: Preconstruction | F10: =IF('GCs Input, Staff & IT Costs'!C10=TRUE,'GCs Input, Staff & IT Costs'!E10,"None") -> None | G10: Flat fee | H10: =IF(F10="None",0,'GCs Input, Staff & IT Costs'!F10) -> 0 | I10: =+H10*10 -> 0 | J10: =IF('Project Info Input'!C25=0,0,+I10) -> 0 | L10: =+J10+K10 -> 0 | P10: =IF(L10=0,"remove","keep") -> remove
P11: keep
B12: Project Executive | F12: =IF('GCs Input, Staff & IT Costs'!C14=TRUE,'GCs Input, Staff & IT Costs'!E14,"None") -> None | G12: Flat fee | H12: =IF(F12="None",0,'GCs Input, Staff & IT Costs'!F14) -> 0 | I12: =IFERROR(+H12*1.4,0) -> 0 | J12: =IF('Project Info Input'!C25=0,0,IFERROR(I12*F12,0)) -> 0 | L12: =+J12+K12 -> 0 | P12: =IF(L12=0,"remove","keep") -> remove
P13: keep
B14: General Super | F14: =IF('GCs Input, Staff & IT Costs'!C11=TRUE,'GCs Input, Staff & IT Costs'!E11,"None") -> None | G14: ='GCs Input, Staff & IT Costs'!D11 -> 0 | H14: =IF(F14="None",0,'GCs Input, Staff & IT Costs'!F11) -> 0 | I14: =IFERROR(+H14*1.4,0) -> 0 | J14: =IF('Project Info Input'!C25=0,0,+I14) -> 0 | L14: =IFERROR(J14*G14,0)+(K14*G14) -> 0 | P14: =IF(L14=0,"remove","keep") -> remove
P15: keep
B16: Safety Manager | F16: =IF('GCs Input, Staff & IT Costs'!C12=TRUE,'GCs Input, Staff & IT Costs'!E12,"None") -> None | G16: ='GCs Input, Staff & IT Costs'!D12 -> 0 | H16: =IF(F16="None",0,'GCs Input, Staff & IT Costs'!F12) -> 0 | I16: =IFERROR(+H16*1.4,0) -> 0 | J16: =IF('Project Info Input'!C25=0,0,+I16) -> 0 | L16: =IFERROR(J16*G16,0)+(K16*G16) -> 0 | P16: =IF(L16=0,"remove","keep") -> remove
P17: keep
B18: Compliance | F18: =IF('GCs Input, Staff & IT Costs'!C13=TRUE,'GCs Input, Staff & IT Costs'!E13,"None") -> None | G18: ='GCs Input, Staff & IT Costs'!D13 -> 0 | H18: =IF(F18="None",0,'GCs Input, Staff & IT Costs'!F13) -> 0 | I18: =IFERROR(+H18*1.4,0) -> 0 | J18: =IF('Project Info Input'!C25=0,0,+I18) -> 0 | L18: =IFERROR(J18*G18,0)+(K18*G18) -> 0 | P18: =IF(L18=0,"remove","keep") -> remove
P19: keep
B20: On-Site Safety | F20: =IF('GCs Input, Staff & IT Costs'!C16=TRUE,'GCs Input, Staff & IT Costs'!E16,"None") -> None | G20: =G21 -> 0 | H20: =SUM(H21:H26) -> 0 | J20: =IF('Project Info Input'!C25=0,0,SUM(J21:J26)) -> 0 | K20: =SUM(K21:K26) -> 0 | L20: =SUM(L21:L26) -> 0 | P20: =IF(L21=0,"remove","keep") -> remove
B21: Salary | G21: ='GCs Input, Staff & IT Costs'!D16 -> 0 | H21: =IF(F20="None",0,'GCs Input, Staff & IT Costs'!F16) -> 0 | I21: =IFERROR(+H21*1.4,0) -> 0 | J21: =IFERROR(I21*F20,0) -> 0 | L21: =IFERROR(J21*G21,0)+(K21*G21) -> 0
B22: Vehicle | G22: =G21 -> 0 | H22: =IF(F20="None",0,'GCs Input, Staff & IT Costs'!$C$36) -> 0 | J22: =IFERROR(+H22*$F$20,0) -> 0 | L22: =IFERROR(J22*G22,0)+(K22*G22) -> 0 | P22: =IF(L22=0,"remove","keep") -> remove
B23: Fuel | G23: =G22 -> 0 | H23: =IF(F20="None",0,'GCs Input, Staff & IT Costs'!$C$37) -> 0 | J23: =IFERROR(+H23*$F$20,0) -> 0 | L23: =IFERROR(J23*G23,0)+(K23*G23) -> 0 | P23: =IF(L23=0,"remove","keep") -> remove
B24: Phone | G24: =G23 -> 0 | H24: =IF(F20="None",0,'GCs Input, Staff & IT Costs'!$C$38) -> 0 | J24: =IFERROR(+H24*$F$20,0) -> 0 | L24: =IFERROR(J24*G24,0)+(K24*G24) -> 0 | P24: =IF(L24=0,"remove","keep") -> remove
B25: Travel & Per Diem | G25: =G24 -> 0 | H25: =IF(F20="None",0,'GCs Input, Staff & IT Costs'!$C$39) -> 0 | J25: =IFERROR(+H25,0) -> 0 | L25: =IFERROR(J25*G25,0)+(K25*G25) -> 0 | P25: =IF(L25=0,"remove","keep") -> remove
B26: Temporary Housing | G26: =G25 -> 0 | H26: =IF(F20="None",0,'GCs Input, Staff & IT Costs'!$C$41) -> 0 | J26: =IFERROR(+H26*$F$20,0) -> 0 | L26: =IFERROR(J26*G26,0)+(K26*G26) -> 0 | P26: =IF(L26=0,"remove","keep") -> remove
P27: keep
B28: Senior Project Manager | F28: =IF('GCs Input, Staff & IT Costs'!C18=TRUE,'GCs Input, Staff & IT Costs'!E18,"None") -> None | G28: =G29 -> 0 | H28: =SUM(H29:H34) -> 0 | J28: =IF('Project Info Input'!C25=0,0,SUM(J29:J34)) -> 0 | K28: =SUM(K29:K34) -> 0 | L28: =SUM(L29:L34) -> 0 | P28: =IF(L29=0,"remove","keep") -> remove
B29: Salary | G29: ='GCs Input, Staff & IT Costs'!D18 -> 0 | H29: =IF(F28="None",0,'GCs Input, Staff & IT Costs'!F18) -> 0 | I29: =IFERROR(+H29*1.4,0) -> 0 | J29: =IFERROR(I29*F28,0) -> 0 | L29: =IFERROR(J29*G29,0)+(K29*G29) -> 0
B30: Vehicle | G30: =G29 -> 0 | H30: =IF(F28="None",0,'GCs Input, Staff & IT Costs'!$C$36) -> 0 | J30: =IFERROR(+H30*$F$28,0) -> 0 | L30: =IFERROR(J30*G30,0)+(K30*G30) -> 0 | P30: =IF(L30=0,"remove","keep") -> remove
B31: Fuel | G31: =G30 -> 0 | H31: =IF(F28="None",0,'GCs Input, Staff & IT Costs'!$C$37) -> 0 | J31: =IFERROR(+H31*$F$28,0) -> 0 | L31: =IFERROR(J31*G31,0)+(K31*G31) -> 0 | P31: =IF(L31=0,"remove","keep") -> remove
B32: Phone | G32: =G31 -> 0 | H32: =IF(F28="None",0,'GCs Input, Staff & IT Costs'!$C$38) -> 0 | J32: =IFERROR(+H32*$F$28,0) -> 0 | L32: =IFERROR(J32*G32,0)+(K32*G32) -> 0 | P32: =IF(L32=0,"remove","keep") -> remove
B33: Travel & Per Diem | G33: =G32 -> 0 | H33: =IF(F28="None",0,'GCs Input, Staff & IT Costs'!$C$39) -> 0 | J33: =IFERROR(+H33,0) -> 0 | L33: =IFERROR(J33*G33,0)+(K33*G33) -> 0 | P33: =IF(L33=0,"remove","keep") -> remove
B34: Temporary Housing | G34: =G33 -> 0 | H34: =IF(F28="None",0,'GCs Input, Staff & IT Costs'!$C$42) -> 0 | J34: =IFERROR(+H34*$F$28,0) -> 0 | L34: =IFERROR(J34*G34,0)+(K34*G34) -> 0 | P34: =IF(L34=0,"remove","keep") -> remove
P35: keep
B36: Project Manager | F36: =IF('GCs Input, Staff & IT Costs'!C19=TRUE,'GCs Input, Staff & IT Costs'!E19,"None") -> None | G36: =G37 -> 0 | H36: =SUM(H37:H42) -> 0 | J36: =IF('Project Info Input'!C25=0,0,SUM(J37:J42)) -> 0 | K36: =SUM(K37:K42) -> 0 | L36: =SUM(L37:L42) -> 0 | P36: =IF(L37=0,"remove","keep") -> remove
B37: Salary | G37: ='GCs Input, Staff & IT Costs'!D19 -> 0 | H37: =IF(F36="None",0,'GCs Input, Staff & IT Costs'!F19) -> 0 | I37: =IFERROR(+H37*1.4,0) -> 0 | J37: =IFERROR(I37*F36,0) -> 0 | L37: =IFERROR(J37*G37,0)+(K37*G37) -> 0
B38: Vehicle | G38: =G37 -> 0 | H38: =IF(F36="None",0,'GCs Input, Staff & IT Costs'!$C$36) -> 0 | J38: =IFERROR(+H38*$F$36,0) -> 0 | L38: =IFERROR(J38*G38,0)+(K38*G38) -> 0 | P38: =IF(L38=0,"remove","keep") -> remove
B39: Fuel | G39: =G38 -> 0 | H39: =IF(F36="None",0,'GCs Input, Staff & IT Costs'!$C$37) -> 0 | J39: =IFERROR(+H39*$F$36,0) -> 0 | L39: =IFERROR(J39*G39,0)+(K39*G39) -> 0 | P39: =IF(L39=0,"remove","keep") -> remove
B40: Phone | G40: =G39 -> 0 | H40: =IF(F36="None",0,'GCs Input, Staff & IT Costs'!$C$38) -> 0 | J40: =IFERROR(+H40*$F$36,0) -> 0 | L40: =IFERROR(J40*G40,0)+(K40*G40) -> 0 | P40: =IF(L40=0,"remove","keep") -> remove
B41: Travel & Per Diem | G41: =G40 -> 0 | H41: =IF(F36="None",0,'GCs Input, Staff & IT Costs'!$C$39) -> 0 | J41: =IFERROR(+H41,0) -> 0 | L41: =IFERROR(J41*G41,0)+(K41*G41) -> 0 | P41: =IF(L41=0,"remove","keep") -> remove
B42: Temporary Housing | G42: =G41 -> 0 | H42: =IF(F36="None",0,'GCs Input, Staff & IT Costs'!$C$43) -> 0 | J42: =IFERROR(+H42*$F$36,0) -> 0 | L42: =IFERROR(J42*G42,0)+(K42*G42) -> 0 | P42: =IF(L42=0,"remove","keep") -> remove
P43: keep
B44: Assistant Project Manager | F44: =IF('GCs Input, Staff & IT Costs'!C20=TRUE,'GCs Input, Staff & IT Costs'!E20,"None") -> None | G44: =G45 -> 0 | H44: =SUM(H45:H50) -> 0 | J44: =IF('Project Info Input'!C25=0,0,SUM(J45:J50)) -> 0 | K44: =SUM(K45:K50) -> 0 | L44: =SUM(L45:L50) -> 0 | P44: =IF(L45=0,"remove","keep") -> remove
B45: Salary | G45: ='GCs Input, Staff & IT Costs'!D20 -> 0 | H45: =IF(F44="None",0,'GCs Input, Staff & IT Costs'!F20) -> 0 | I45: =IFERROR(+H45*1.4,0) -> 0 | J45: =IFERROR(I45*F44,0) -> 0 | L45: =IFERROR(J45*G45,0)+(K45*G45) -> 0
B46: Vehicle | G46: =G45 -> 0 | H46: =IF(F44="None",0,'GCs Input, Staff & IT Costs'!$C$36) -> 0 | J46: =IFERROR(+H46*$F$44,0) -> 0 | L46: =IFERROR(J46*G46,0)+(K46*G46) -> 0 | P46: =IF(L46=0,"remove","keep") -> remove
B47: Fuel | G47: =G46 -> 0 | H47: =IF(F44="None",0,'GCs Input, Staff & IT Costs'!$C$37) -> 0 | J47: =IFERROR(+H47*$F$44,0) -> 0 | L47: =IFERROR(J47*G47,0)+(K47*G47) -> 0 | P47: =IF(L47=0,"remove","keep") -> remove
B48: Phone | G48: =G47 -> 0 | H48: =IF(F44="None",0,'GCs Input, Staff & IT Costs'!$C$38) -> 0 | J48: =IFERROR(+H48*$F$44,0) -> 0 | L48: =IFERROR(J48*G48,0)+(K48*G48) -> 0 | P48: =IF(L48=0,"remove","keep") -> remove
B49: Travel & Per Diem | G49: =G48 -> 0 | H49: =IF(F44="None",0,'GCs Input, Staff & IT Costs'!$C$39) -> 0 | J49: =IFERROR(+H49,0) -> 0 | L49: =IFERROR(J49*G49,0)+(K49*G49) -> 0 | P49: =IF(L49=0,"remove","keep") -> remove
B50: Temporary Housing | G50: =G49 -> 0 | H50: =IF(F44="None",0,'GCs Input, Staff & IT Costs'!$C$44) -> 0 | J50: =IFERROR(+H50*$F$44,0) -> 0 | L50: =IFERROR(J50*G50,0)+(K50*G50) -> 0 | P50: =IF(L50=0,"remove","keep") -> remove
P51: keep
B52: Assistant Project Manager | F52: =IF('GCs Input, Staff & IT Costs'!C21=TRUE,'GCs Input, Staff & IT Costs'!E21,"None") -> None | G52: =G53 -> 0 | H52: =SUM(H53:H58) -> 0 | J52: =IF('Project Info Input'!C25=0,0,SUM(J53:J58)) -> 0 | K52: =SUM(K53:K58) -> 0 | L52: =SUM(L53:L58) -> 0 | P52: =IF(L53=0,"remove","keep") -> remove
B53: Salary | G53: ='GCs Input, Staff & IT Costs'!D21 -> 0 | H53: =IF(F52="None",0,'GCs Input, Staff & IT Costs'!F20) -> 0 | I53: =IFERROR(+H53*1.4,0) -> 0 | J53: =IFERROR(I53*F52,0) -> 0 | L53: =IFERROR(J53*G53,0)+(K53*G53) -> 0
B54: Vehicle | G54: =G53 -> 0 | H54: =IF(F52="None",0,'GCs Input, Staff & IT Costs'!$C$36) -> 0 | J54: =IFERROR(+H54*$F$52,0) -> 0 | L54: =IFERROR(J54*G54,0)+(K54*G54) -> 0 | P54: =IF(L54=0,"remove","keep") -> remove
B55: Fuel | G55: =G54 -> 0 | H55: =IF(F52="None",0,'GCs Input, Staff & IT Costs'!$C$37) -> 0 | J55: =IFERROR(+H55*$F$52,0) -> 0 | L55: =IFERROR(J55*G55,0)+(K55*G55) -> 0 | P55: =IF(L55=0,"remove","keep") -> remove
B56: Phone | G56: =G55 -> 0 | H56: =IF(F52="None",0,'GCs Input, Staff & IT Costs'!$C$38) -> 0 | J56: =IFERROR(+H56*$F$52,0) -> 0 | L56: =IFERROR(J56*G56,0)+(K56*G56) -> 0 | P56: =IF(L56=0,"remove","keep") -> remove
B57: Travel & Per Diem | G57: =G56 -> 0 | H57: =IF(F52="None",0,'GCs Input, Staff & IT Costs'!$C$39) -> 0 | J57: =IFERROR(+H57,0) -> 0 | L57: =IFERROR(J57*G57,0)+(K57*G57) -> 0 | P57: =IF(L57=0,"remove","keep") -> remove
B58: Temporary Housing | G58: =G57 -> 0 | H58: =IF(F52="None",0,'GCs Input, Staff & IT Costs'!$C$44) -> 0 | J58: =IFERROR(+H58*$F$52,0) -> 0 | L58: =IFERROR(J58*G58,0)+(K58*G58) -> 0 | P58: =IF(L58=0,"remove","keep") -> remove
P59: keep
B60: Senior Superintendent | F60: =IF('GCs Input, Staff & IT Costs'!C23=TRUE,'GCs Input, Staff & IT Costs'!E23,"None") -> None | G60: =G61 -> 0 | H60: =SUM(H61:H66) -> 0 | J60: =IF('Project Info Input'!C25=0,0,SUM(J61:J66)) -> 0 | K60: =SUM(K61:K66) -> 0 | L60: =SUM(L61:L66) -> 0 | P60: =IF(L61=0,"remove","keep") -> remove
B61: Salary | G61: ='GCs Input, Staff & IT Costs'!D23 -> 0 | H61: =IF(F60="None",0,'GCs Input, Staff & IT Costs'!F23) -> 0 | I61: =IFERROR(+H61*1.4,0) -> 0 | J61: =IFERROR(I61*F60,0) -> 0 | L61: =IFERROR(J61*G61,0)+(K61*G61) -> 0
B62: Vehicle | G62: =G61 -> 0 | H62: =IF(F60="None",0,'GCs Input, Staff & IT Costs'!$C$36) -> 0 | J62: =IFERROR(+H62*$F$60,0) -> 0 | L62: =IFERROR(J62*G62,0)+(K62*G62) -> 0 | P62: =IF(L62=0,"remove","keep") -> remove
B63: Fuel | G63: =G62 -> 0 | H63: =IF(F60="None",0,'GCs Input, Staff & IT Costs'!$C$37) -> 0 | J63: =IFERROR(+H63*$F$60,0) -> 0 | L63: =IFERROR(J63*G63,0)+(K63*G63) -> 0 | P63: =IF(L63=0,"remove","keep") -> remove
B64: Phone | G64: =G63 -> 0 | H64: =IF(F60="None",0,'GCs Input, Staff & IT Costs'!$C$38) -> 0 | J64: =IFERROR(+H64*$F$60,0) -> 0 | L64: =IFERROR(J64*G64,0)+(K64*G64) -> 0 | P64: =IF(L64=0,"remove","keep") -> remove
B65: Travel & Per Diem | G65: =G64 -> 0 | H65: =IF(F60="None",0,'GCs Input, Staff & IT Costs'!$C$39) -> 0 | J65: =IFERROR(+H65*$F$60,0) -> 0 | L65: =IFERROR(J65*G65,0)+(K65*G65) -> 0 | P65: =IF(L65=0,"remove","keep") -> remove
B66: Temporary Housing | G66: =G65 -> 0 | H66: =IF(F60="None",0,'GCs Input, Staff & IT Costs'!$C$45) -> 0 | J66: =IFERROR(+H66*$F$60,0) -> 0 | L66: =IFERROR(J66*G66,0)+(K66*G66) -> 0 | P66: =IF(L66=0,"remove","keep") -> remove
P67: keep
B68: Superintendent | F68: =IF('GCs Input, Staff & IT Costs'!C24=TRUE,'GCs Input, Staff & IT Costs'!E24,"None") -> None | G68: =G69 -> 0 | H68: =SUM(H69:H74) -> 0 | J68: =IF('Project Info Input'!C25=0,0,SUM(J69:J74)) -> 0 | K68: =SUM(K69:K74) -> 0 | L68: =SUM(L69:L74) -> 0 | P68: =IF(L69=0,"remove","keep") -> remove
B69: Salary | G69: ='GCs Input, Staff & IT Costs'!D24 -> 0 | H69: =IF(F68="None",0,'GCs Input, Staff & IT Costs'!F24) -> 0 | I69: =IFERROR(+H69*1.4,0) -> 0 | J69: =IFERROR(I69*F68,0) -> 0 | L69: =IFERROR(J69*G69,0)+(K69*G69) -> 0
B70: Vehicle | G70: =G69 -> 0 | H70: =IF(F68="None",0,'GCs Input, Staff & IT Costs'!$C$36) -> 0 | J70: =IFERROR(+H70*$F$68,0) -> 0 | L70: =IFERROR(J70*G70,0)+(K70*G70) -> 0 | P70: =IF(L70=0,"remove","keep") -> remove
B71: Fuel | G71: =G70 -> 0 | H71: =IF(F68="None",0,'GCs Input, Staff & IT Costs'!$C$37) -> 0 | J71: =IFERROR(+H71*$F$68,0) -> 0 | L71: =IFERROR(J71*G71,0)+(K71*G71) -> 0 | P71: =IF(L71=0,"remove","keep") -> remove
B72: Phone | G72: =G71 -> 0 | H72: =IF(F68="None",0,'GCs Input, Staff & IT Costs'!$C$38) -> 0 | J72: =IFERROR(+H72*$F$68,0) -> 0 | L72: =IFERROR(J72*G72,0)+(K72*G72) -> 0 | P72: =IF(L72=0,"remove","keep") -> remove
B73: Travel & Per Diem | G73: =G72 -> 0 | H73: =IF(F68="None",0,'GCs Input, Staff & IT Costs'!$C$39) -> 0 | J73: =IFERROR(+H73*$F$68,0) -> 0 | L73: =IFERROR(J73*G73,0)+(K73*G73) -> 0 | P73: =IF(L73=0,"remove","keep") -> remove
B74: Temporary Housing | G74: =G73 -> 0 | H74: =IF(F68="None",0,'GCs Input, Staff & IT Costs'!$C$46) -> 0 | J74: =IFERROR(+H74*$F$68,0) -> 0 | L74: =IFERROR(J74*G74,0)+(K74*G74) -> 0 | P74: =IF(L74=0,"remove","keep") -> remove
P75: keep
B76: Assistant Superintedent | F76: =IF('GCs Input, Staff & IT Costs'!C25=TRUE,'GCs Input, Staff & IT Costs'!E25,"None") -> None | G76: =G77 -> 0 | H76: =SUM(H77:H82) -> 0 | J76: =IF('Project Info Input'!C25=0,0,SUM(J77:J82)) -> 0 | K76: =SUM(K77:K82) -> 0 | L76: =SUM(L77:L82) -> 0 | P76: =IF(L77=0,"remove","keep") -> remove
B77: Salary | G77: ='GCs Input, Staff & IT Costs'!D25 -> 0 | H77: =IF(F76="None",0,'GCs Input, Staff & IT Costs'!F25) -> 0 | I77: =IFERROR(+H77*1.4,0) -> 0 | J77: =IFERROR(I77*F76,0) -> 0 | L77: =IFERROR(J77*G77,0)+(K77*G77) -> 0
B78: Vehicle | G78: =G77 -> 0 | H78: =IF(F76="None",0,'GCs Input, Staff & IT Costs'!$C$36) -> 0 | J78: =IFERROR(+H78*$F$76,0) -> 0 | L78: =IFERROR(J78*G78,0)+(K78*G78) -> 0 | P78: =IF(L78=0,"remove","keep") -> remove
B79: Fuel | G79: =G78 -> 0 | H79: =IF(F76="None",0,'GCs Input, Staff & IT Costs'!$C$37) -> 0 | J79: =IFERROR(+H79*$F$76,0) -> 0 | L79: =IFERROR(J79*G79,0)+(K79*G79) -> 0 | P79: =IF(L79=0,"remove","keep") -> remove
B80: Phone | G80: =G79 -> 0 | H80: =IF(F76="None",0,'GCs Input, Staff & IT Costs'!$C$38) -> 0 | J80: =IFERROR(+H80*$F$76,0) -> 0 | L80: =IFERROR(J80*G80,0)+(K80*G80) -> 0 | P80: =IF(L80=0,"remove","keep") -> remove
B81: Travel & Per Diem | G81: =G80 -> 0 | H81: =IF(F76="None",0,'GCs Input, Staff & IT Costs'!$C$39) -> 0 | J81: =IFERROR(+H81*$F$76,0) -> 0 | L81: =IFERROR(J81*G81,0)+(K81*G81) -> 0 | P81: =IF(L81=0,"remove","keep") -> remove
B82: Temporary Housing | G82: =G81 -> 0 | H82: =IF(F76="None",0,'GCs Input, Staff & IT Costs'!$C$47) -> 0 | J82: =IFERROR(+H82*$F$76,0) -> 0 | L82: =IFERROR(J82*G82,0)+(K82*G82) -> 0 | P82: =IF(L82=0,"remove","keep") -> remove
P83: keep
B84: Assistant Superintedent | F84: =IF('GCs Input, Staff & IT Costs'!C26=TRUE,'GCs Input, Staff & IT Costs'!E26,"None") -> None | G84: =G85 -> 0 | H84: =SUM(H85:H90) -> 0 | J84: =IF('Project Info Input'!C25=0,0,SUM(J85:J90)) -> 0 | K84: =SUM(K85:K90) -> 0 | L84: =SUM(L85:L90) -> 0 | P84: =IF(L85=0,"remove","keep") -> remove
B85: Salary | G85: ='GCs Input, Staff & IT Costs'!D26 -> 0 | H85: =IF(F84="None",0,'GCs Input, Staff & IT Costs'!F25) -> 0 | I85: =IFERROR(+H85*1.4,0) -> 0 | J85: =IFERROR(I85*F84,0) -> 0 | L85: =IFERROR(J85*G85,0)+(K85*G85) -> 0
B86: Vehicle | G86: =G85 -> 0 | H86: =IF(F84="None",0,'GCs Input, Staff & IT Costs'!$C$36) -> 0 | J86: =IFERROR(+H86*$F$84,0) -> 0 | L86: =IFERROR(J86*G86,0)+(K86*G86) -> 0 | P86: =IF(L86=0,"remove","keep") -> remove
B87: Fuel | G87: =G86 -> 0 | H87: =IF(F84="None",0,'GCs Input, Staff & IT Costs'!$C$37) -> 0 | J87: =IFERROR(+H87*$F$84,0) -> 0 | L87: =IFERROR(J87*G87,0)+(K87*G87) -> 0 | P87: =IF(L87=0,"remove","keep") -> remove
B88: Phone | G88: =G87 -> 0 | H88: =IF(F84="None",0,'GCs Input, Staff & IT Costs'!$C$38) -> 0 | J88: =IFERROR(+H88*$F$84,0) -> 0 | L88: =IFERROR(J88*G88,0)+(K88*G88) -> 0 | P88: =IF(L88=0,"remove","keep") -> remove
B89: Travel & Per Diem | G89: =G88 -> 0 | H89: =IF(F84="None",0,'GCs Input, Staff & IT Costs'!$C$39) -> 0 | J89: =IFERROR(+H89*$F$84,0) -> 0 | L89: =IFERROR(J89*G89,0)+(K89*G89) -> 0 | P89: =IF(L89=0,"remove","keep") -> remove
B90: Temporary Housing | G90: =G89 -> 0 | H90: =IF(F84="None",0,'GCs Input, Staff & IT Costs'!$C$47) -> 0 | J90: =IFERROR(+H90*$F$84,0) -> 0 | L90: =IFERROR(J90*G90,0)+(K90*G90) -> 0 | P90: =IF(L90=0,"remove","keep") -> remove
P91: keep
B92: Project Coordinator | F92: =IF('GCs Input, Staff & IT Costs'!C29=TRUE,'GCs Input, Staff & IT Costs'!E29,"None") -> None | G92: ='GCs Input, Staff & IT Costs'!D29 -> 0 | H92: =IF(F92="None",0,'GCs Input, Staff & IT Costs'!F29) -> 0 | I92: =IFERROR(+H92*1.4,0) -> 0 | J92: =IF('Project Info Input'!C25=0,0,IFERROR(I92*F92,0)) -> 0 | L92: =IFERROR(J92*G92,0)+(K92*G92) -> 0 | P92: =IF(L92=0,"remove","keep") -> remove
B94: Field Clerk | F94: =IF('GCs Input, Staff & IT Costs'!C28=TRUE,'GCs Input, Staff & IT Costs'!E28,"None") -> None | G94: ='GCs Input, Staff & IT Costs'!D28 -> 0 | H94: =IF(F94="None",0,'GCs Input, Staff & IT Costs'!F28) -> 0 | I94: =IFERROR(+H94*1.4,0) -> 0 | J94: =IF('Project Info Input'!C25=0,0,IFERROR(I94*F94,0)) -> 0 | L94: =IFERROR(J94*G94,0)+(K94*G94) -> 0 | P94: =IF(L94=0,"remove","keep") -> remove
B96: Accounting | F96: =IF('GCs Input, Staff & IT Costs'!C30=TRUE,'GCs Input, Staff & IT Costs'!E30,"None") -> None | G96: ='GCs Input, Staff & IT Costs'!D30 -> 0 | H96: =IF(F96="None",0,'GCs Input, Staff & IT Costs'!F30) -> 0 | I96: =IFERROR(+H96*1.4,0) -> 0 | J96: =IF('Project Info Input'!C25=0,0,IFERROR(I96*F96,0)) -> 0 | L96: =IFERROR(J96*G96,0)+(K96*G96) -> 0 | P96: =IF(L96=0,"remove","keep") -> remove
B98: Temporary Labor | F98: =IF('GCs Input, Staff & IT Costs'!C32=TRUE,'GCs Input, Staff & IT Costs'!E32,"None") -> None | G98: ='GCs Input, Staff & IT Costs'!D32 -> 0 | H98: =IF(F98="None",0,'GCs Input, Staff & IT Costs'!F32) -> 0 | I98: =IFERROR(+H98*1.4,0) -> 0 | J98: =IF('Project Info Input'!C25=0,0,IFERROR(I98*F98,0)) -> 0 | L98: =IFERROR(J98*G98,0)+(K98*G98) -> 0 | P98: =IF(L98=0,"remove","keep") -> remove
P99: keep
B100: Total Personnel Costs | G100: =+'GCs Input, Staff & IT Costs'!C6&" months" -> 0 months | H100: =IF('Project Info Input'!C25=0,0,+L100/'GCs Input, Staff & IT Costs'!$C$6) -> 0 | I100: per month | L100: =+L10+L14+L16+L18+L20+L12+L28+L36+L44+L52+L60+L68+L76+L84+L98+L92+L94+L96 -> 0 | P100: =IF(L100=0,"remove","keep") -> remove
P101: keep
B102: Other Costs | F102: % of Month | G102: # of Months | H102: Monthly Rate | I102: # of People | J102: Project Rate | K102: Adjustments | L102: Total | P102: =IF(L102=0,"remove","keep") -> keep
P103: keep
B104: Field Office Rental | F104: 1 | G104: ='GCs Input, Staff & IT Costs'!$C$6 -> 0 | H104: =+'GCs Input, Staff & IT Costs'!C49 -> 1500 | J104: =IF('Project Info Input'!C25=0,0,+H104) -> 0 | L104: =IFERROR(J104*G104,0)+(K104*G104) -> 0 | P104: =IF(L104=0,"remove","keep") -> remove
...

Sheet Estimate Risk Summary
B2: ESTIMATE RISK SUMMARY
B4: Project | C4: ='Project Info Input'!C8 -> Test
B5: Lead Estimator Name | C5: ='Project Info Input'!C12 -> 0
B6: Reviewing Estimator Name | C6: ='Project Info Input'!C13 -> 0
B8: Scope | C8: # of Bids | D8: % Spread Btwn Low Bids | E8: Adjustments | F8: Bid Day Cuts | G8: Exposure/Risk | H8: Savings | I8: Anticipated Buy Out | J8: Comment | O8: PROJECT NAME | P8: LOCATION | Q8: VOLUME | R8: FEE | S8: FEE ON ALLOWANCES | T8: TOTAL FEE | U8: FEE % | V8: BID DAY BUYOUT | W8: FEE + 1/2 BUYOUT | X8: FEE + BUYOUT | Y8: PROJECTED START
B9: Demolition | E9: =Estimate!M35 -> 0 | F9: =Estimate!M36 -> 0 | G9: DELETE | I9: MANUAL PLUG | J9: ADD SUB CARRIED | O9: ='Budget Summary'!E3 -> Test | P9: ='Budget Summary'!E4 -> Test 1 | Q9: ='Budget Summary'!G2 -> 6568.0722 | R9: =Estimate!N1247 -> 312.76534 | S9: =Estimate!N1253-(Estimate!N1253/(1+U9)) -> 0 | T9: =R9+S9 -> 312.76534 | U9: =Estimate!G1249+Estimate!G1250 -> 0.05 | V9: =I45 -> 0 | W9: =T9+V9*0.5 -> 312.76534 | X9: =T9+V9 -> 312.76534 | Y9: ='Project Info Input'!C19 -> 0
B10: Earthwork | E10: =Estimate!M92+Estimate!M51 -> 0 | F10: =Estimate!M93+Estimate!M52 -> 0 | G10: =F10 -> 0 | I10: =G10+H10 -> 0 | O10: ='Budget Summary'!E4 -> Test 1 | P10: ='Budget Summary'!E5 -> 0 | Q10: ='Budget Summary'!G3 -> 0 | R10: =Estimate!N1248 -> 312.76534 | S10: =Estimate!N1254-(Estimate!N1254/(1+U10)) -> 0 | T10: =R10+S10 -> 312.76534 | U10: =Estimate!G1250+Estimate!G1251 -> 0.03 | V10: =I46 -> 0 | W10: =T10+V10*0.5 -> 312.76534 | X10: =T10+V10 -> 312.76534 | Y10: ='Project Info Input'!C20 -> 0
B11: Storm Sewer | E11: =Estimate!M138 -> 0 | F11: =Estimate!M139 -> 0 | G11: =F11 -> 0 | I11: =G11+H11 -> 0
B12: Fire Water | E12: =Estimate!M162 -> 0 | F12: =Estimate!M163 -> 0 | G12: =F12 -> 0 | I12: =G12+H12 -> 0
B13: Domestic Water | E13: =Estimate!M174 -> 0 | F13: =Estimate!M175 -> 0 | G13: =F13 -> 0 | I13: =G13+H13 -> 0
B14: Sanitary Sewer | E14: =Estimate!M196 -> 0 | F14: =Estimate!M197 -> 0 | G14: =F14 -> 0 | I14: =G14+H14 -> 0
B15: Site Concrete | E15: =Estimate!M230 -> 0 | F15: =Estimate!M231 -> 0 | G15: =F15 -> 0 | I15: =G15+H15 -> 0 | O15: PRECON BUDGET
B16: Asphalt Paving | E16: =Estimate!M245+Estimate!M262 -> 0 | F16: =Estimate!M246+Estimate!M263 -> 0 | G16: =F16 -> 0 | I16: =G16+H16 -> 0 | O16: Design Coord. | P16: =Estimate!M1229 -> 0
B17: Landscaping | E17: =Estimate!M281 -> 0 | F17: =Estimate!M282 -> 0 | G17: =F17 -> 0 | I17: =G17+H17 -> 0 | O17: GC's | P17: ='General Conditions'!L10 -> 0
B18: Fencing | E18: =Estimate!M297 -> 0 | F18: =Estimate!M298 -> 0 | G18: =F18 -> 0 | I18: =G18+H18 -> 0 | O18: TOTAL | P18: =P16+P17 -> 0
B19: Retaining Walls | E19: =Estimate!M307 -> 0 | F19: =Estimate!M308 -> 0 | G19: =F19 -> 0 | I19: =G19+H19 -> 0
B20: Misc Site Improvements | E20: =Estimate!M324 -> 0 | F20: =Estimate!M325 -> 0 | G20: =F20 -> 0 | I20: =G20+H20 -> 0
B21: Concrete | E21: =Estimate!M358+Estimate!M378+Estimate!M386+Estimate!M400+Estimate!M413 -> 0 | F21: =Estimate!M359+Estimate!M379+Estimate!M387+Estimate!M401+Estimate!M414 -> 0 | G21: =F21 -> 0 | I21: =G21+H21 -> 0
B22: Masonry | E22: =Estimate!M424 -> 0 | F22: =Estimate!M425 -> 0 | G22: =F22 -> 0 | I22: =G22+H22 -> 0
B23: Structural & Misc Steel / Erection | E23: =Estimate!M451+Estimate!M474+Estimate!M506 -> 0 | F23: =Estimate!M452+Estimate!M475+Estimate!M507 -> 0 | G23: =F23 -> 0 | I23: =G23+H23 -> 0
B24: Joists & Decking | E24: =Estimate!M491 -> 0 | F24: =Estimate!M492 -> 0 | G24: =F24 -> 0 | I24: =G24+H24 -> 0
B25: Finish Carpentry | E25: =Estimate!M535 -> 0 | F25: =Estimate!M536 -> 0 | G25: =F25 -> 0 | I25: =G25+H25 -> 0
B26: Water & Fireproofiong | E26: =Estimate!M577 -> 0 | F26: =Estimate!M578 -> 0 | G26: =F26 -> 0 | I26: =G26+H26 -> 0
B27: Metal Panels & Canopies | E27: =Estimate!M578+Estimate!M566 -> 0 | F27: =Estimate!M579+Estimate!M567 -> 0 | G27: =F27 -> 0 | I27: =G27+H27 -> 0
B28: Roofing | E28: =Estimate!M603 -> 0 | F28: =Estimate!M604 -> 0 | G28: =F28 -> 0 | I28: =G28+H28 -> 0
B29: Caulking | E29: =Estimate!M619 -> 0 | F29: =Estimate!M620 -> 0 | G29: =F29 -> 0 | I29: =G29+H29 -> 0
B30: Doors & Frames | E30: =Estimate!M661+Estimate!M631 -> 0 | F30: =Estimate!M662+Estimate!M632 -> 0 | G30: =F30 -> 0 | I30: =G30+H30 -> 0
B31: Overhead Doors | E31: =Estimate!M631 -> 0 | F31: =Estimate!M632 -> 0 | G31: =F31 -> 0 | I31: =G31+H31 -> 0
B32: Glass & Glazing | E32: =Estimate!M682 -> 0 | F32: =Estimate!M683 -> 0 | G32: =F32 -> 0 | I32: =G32+H32 -> 0
B33: Framing / Drywall / Furnishings | E33: =Estimate!M700+Estimate!M709+Estimate!M877 -> 0 | F33: =Estimate!M701+Estimate!M710+Estimate!M878 -> 0 | G33: =F33 -> 0 | I33: =G33+H33 -> 0
B34: Flooring | E34: =Estimate!M730 -> 0 | F34: =Estimate!M731 -> 0 | G34: =F34 -> 0 | I34: =G34+H34 -> 0
B35: Painting | E35: =Estimate!M749+Estimate!M791 -> 0 | F35: =Estimate!M750+Estimate!M792 -> 0 | G35: =F35 -> 0 | I35: =G35+H35 -> 0
B36: Specialties | E36: =Estimate!M827 -> 0 | F36: =Estimate!M828 -> 0 | G36: =F36 -> 0 | I36: =G36+H36 -> 0
B37: Dock Equipment / Food Service Equip | E37: =Estimate!M850+Estimate!M867 -> 0 | F37: =Estimate!M851+Estimate!M868 -> 0 | G37: =F37 -> 0 | I37: =G37+H37 -> 0
B38: PEMB | E38: =Estimate!M888 -> 0 | F38: =Estimate!M889 -> 0 | G38: =F38 -> 0 | I38: =G38+H38 -> 0
B39: Elevators / Cranes | E39: =Estimate!M906+Estimate!M899 -> 0 | F39: =Estimate!M907+Estimate!M900 -> 0 | G39: =F39 -> 0 | I39: =G39+H39 -> 0
B40: Fire Protection | E40: =Estimate!M927 -> 0 | F40: =Estimate!M928 -> 0 | G40: =F40 -> 0 | I40: =G40+H40 -> 0
B41: Plumbing | E41: =Estimate!M964+Estimate!M985 -> 0 | F41: =Estimate!M965+Estimate!M986 -> 0 | G41: =F41 -> 0 | I41: =G41+H41 -> 0
B42: Mechanical | E42: =Estimate!M1012+Estimate!M1038 -> 0 | F42: =Estimate!M1013+Estimate!M1039 -> 0 | G42: =F42 -> 0 | I42: =G42+H42 -> 0
B43: Electrical | E43: =Estimate!M1062+Estimate!M1103+Estimate!M1076+Estimate!M1124+Estimate!M1152+Estimate!M1166+Estimate!M1176+Estimate!M1188+Estimate!M1196+Estimate!M1205 -> 0 | F43: =Estimate!M1063+Estimate!M1104+Estimate!M1077+Estimate!M1125+Estimate!M1153+Estimate!M1167+Estimate!M1177+Estimate!M1189+Estimate!M1197+Estimate!M1206 -> 0 | G43: =F43 -> 0 | I43: =G43+H43 -> 0
I44: =G44+H44 -> 0
B45: SUBTOTALS (LS) | E45: =SUM(E9:E44) -> 0 | F45: =SUM(F9:F44) -> 0 | G45: =SUM(G9:G44) -> 0 | H45: =SUM(H9:H44) -> 0 | I45: =SUM(I9:I44) -> 0
B47: SUBTOTALS (%)* | E47: =E45/('Budget Summary'!$G$2-'Budget Summary'!$E$88) -> 0 | F47: =F45/('Budget Summary'!$G$2-'Budget Summary'!$E$88) -> 0 | G47: =G45/('Budget Summary'!$G$2-'Budget Summary'!$E$88) -> 0 | H47: =H45/('Budget Summary'!$G$2-'Budget Summary'!$E$88) -> 0 | I47: =I45/('Budget Summary'!$G$2-'Budget Summary'!$E$88) -> 0
B48: * Does not include allowances
B49: Fee Breakdown if ALL Exposure/Risk is Mitigated
B51: Description | D51: OH (LS) | E51: OH (%) | F51: Profit (LS) | G51: Profit (%) | H51: Total Fee (LS) | I51: Total Fee (%) | J51: Fee $/Month | O51: COMBINE OH & PROFIT CELLS/AMOUNTS/%
B52: OH & Profit | D52: =Estimate!J1249 -> 125.10614 | E52: =+Estimate!G1249 -> 0.02 | F52: =Estimate!J1250 -> 187.65921 | G52: =Estimate!G1250 -> 0.03 | H52: =Estimate!N1248 -> 312.76534 | I52: =E52+G52 -> 0.05 | J52: =H52/('Project Info Input'!C22+'Project Info Input'!C23) -> #DIV/0!
B54: Fee Breakdown if NO Exposure/Risk is Mitigated
B56: Description | D56: OH (LS) | E56: OH (%) | F56: Profit (LS) | G56: Profit (%) | H56: Total Fee (LS) | I56: Total Fee (%) | J56: Fee $/Month
B57: OH & Profit | D57: =Estimate!J1249 -> 125.10614 | E57: =+Estimate!G1249 -> 0.02 | F57: =Estimate!J1250+G45 -> 187.65921 | G57: =Estimate!G1250+G47 -> 0.03 | H57: =D57+F57 -> 312.76534 | I57: =E57+G57 -> 0.05 | J57: =H57/('Project Info Input'!C22+'Project Info Input'!C23) -> #DIV/0! | O57: COMBINE OH & PROFIT CELLS/AMOUNTS/%
B59: REVIEWING ESTIMATOR
C60: Signature | J60: Date
G62: TOTAL ANTICIPATED BUYOUT

Sheet How to Use
A1: Sheet Name | B1: Purpose | C1: Instructions
A2: Project Info Input | B2: Input basic project details like client name, project name, and location. | C2: Enter required project information in the highlighted fields.
A3: Budget Summary | B3: Summarizes the project's total budget after inputs. | C3: Review after filling out the 'Estimate' and 'GCs Input' sheets to check the overall budget.
A4: Estimate | B4: Breaks down detailed estimate of project including materials, labor, etc. | C4: Input quantities, unit prices, and descriptions of materials and labor.
A5: Clarifications | B5: Notes or clarifications about the estimate assumptions or conditions. | C5: Add clarifying notes to explain the scope and boundaries of the estimate.
A6: GCs Input, Staff & IT Costs | B6: Input for general conditions, staff salaries, and IT expenses related to the project. | C6: Enter salaries, overheads, and other related general condition costs.
A7: General Conditions | B7: Tracks general costs like overhead and site costs. | C7: Verify automatic calculations from the 'GCs Input' sheet.
A8: Estimate Risk Summary | B8: Summarizes risks that could impact the estimate. | C8: Document risks that might affect the budget or timeline.
